Workbook

Sheet Clientes
A1: ID Cliente | B1: Nombre Cliente | C1: Ciudad | D1: Tipo de Negocio | E1: Ventas 2024 (COP) | F1: % Incremento 2025 | G1: Ingresos 2025 (COP) | H1: % Cartera Vencida | I1: Cartera Vencida (COP) | J1: Días de Pago Promedio | K1: Estado | L1: Última Compra
A2: C001 | B2: Super Todo Fresco | C2: Valledupar | D2: Supermercado | E2: 181400000 | F2: 0.1956 | G2: =E2*(1+F2) -> 216881840 | H2: 0.1155 | I2: =E2*H2 -> 20951700 | J2: 39 | K2: En riesgo | L2: 45759
A3: C002 | B3: Tienda La 84 | C3: Barranquilla | D3: Tienda tradicional | E3: 8800000 | F3: 0.1662 | G3: =E3*(1+F3) -> 10262560 | H3: 0.029 | I3: =E3*H3 -> 255200 | J3: 30 | K3: Activo | L3: 45815
A4: C003 | B4: Supermercado Ahorro Costeño | C4: Barranquilla | D4: Supermercado | E4: 19600000 | F4: 0.1866 | G4: =E4*(1+F4) -> 23257360 | H4: 0.1626 | I4: =E4*H4 -> 3186960 | J4: 32 | K4: Suspendido | L4: 45722
A5: C004 | B5: Minimercado La Popular | C5: Barranquilla | D5: Tienda tradicional | E5: 7400000 | F5: 0.1936 | G5: =E5*(1+F5) -> 8832640 | H5: 0.1943 | I5: =E5*H5 -> 1437820 | J5: 43 | K5: Suspendido | L5: 45760
A6: C005 | B6: Hipermercado La Bonanza | C6: Santa Marta | D6: Supermercado | E6: 26000000 | F6: 0.195 | G6: =E6*(1+F6) -> 31070000 | H6: 0.018 | I6: =E6*H6 -> 468000 | J6: 44 | K6: Activo | L6: 45831
A7: C006 | B7: Tienda La Esquina | C7: Barranquilla | D7: Tienda tradicional | E7: 133100000 | F7: 0.1854 | G7: =E7*(1+F7) -> 157776740 | H7: 0.0724 | I7: =E7*H7 -> 9636440 | J7: 31 | K7: Activo | L7: 45827
A8: C007 | B8: Autoservicio Santa Rita | C8: Barranquilla | D8: Tienda tradicional | E8: 6200000 | F8: 0.1566 | G8: =E8*(1+F8) -> 7170920 | H8: 0.0378 | I8: =E8*H8 -> 234360 | J8: 45 | K8: Activo | L8: 45866
A9: C008 | B9: Autoservicios El Cacique | C9: Barranquilla | D9: Supermercado | E9: 64500000 | F9: 0.1734 | G9: =E9*(1+F9) -> 75684300 | H9: 0.0787 | I9: =E9*H9 -> 5076150 | J9: 31 | K9: Activo | L9: 45708
A10: C009 | B10: Restaurante La Bahía | C10: Barranquilla | D10: Institución | E10: 159200000 | F10: 0.1596 | G10: =E10*(1+F10) -> 184608320 | H10: 0.0147 | I10: =E10*H10 -> 2340240 | J10: 44 | K10: Activo | L10: 45894
A11: C010 | B11: Supermercado La Economía | C11: Barranquilla | D11: Supermercado | E11: 188500000 | F11: 0.1826 | G11: =E11*(1+F11) -> 222920100 | H11: 0.1941 | I11: =E11*H11 -> 36587850 | J11: 30 | K11: Suspendido | L11: 45779
A12: C011 | B12: Autoservicios El Litoral | C12: Barranquilla | D12: Supermercado | E12: 122800000 | F12: 0.1529 | G12: =E12*(1+F12) -> 141576120 | H12: 0.0312 | I12: =E12*H12 -> 3831360 | J12: 42 | K12: Activo | L12: 45890
A13: C012 | B13: Autoservicios El Rey | C13: Barranquilla | D13: Supermercado | E13: 37900000 | F13: 0.1595 | G13: =E13*(1+F13) -> 43945050 | H13: 0.1663 | I13: =E13*H13 -> 6302770 | J13: 36 | K13: Suspendido | L13: 45689
... A151: C150 | B151: Cafetería Empresarial San Fernando | C151: Cartagena | D151: Institución | E151: 183700000 | F151: 0.1964 | G151: =E151*(1+F151) -> 219778680 | H151: 0.1156 | I151: =E151*H151 -> 21235720 | J151: 35 | K151: En riesgo | L151: 45720
A153: Supuestos: % Incremento 2025 e % Cartera Vencida son valores de entrada (fuente: simulación para demo/analítica, no datos reales de Andina Foods S.A.S.). Cartera Vencida (COP) = Ventas 2024 × % Cartera Vencida. Ingresos 2025 (COP) = Ventas 2024 × (1 + % Incremento 2025).

Sheet Resumen
A1: Resumen Ejecutivo — Cartera de Clientes Andina Foods S.A.S.
A3: Total de clientes | B3: =COUNTA(Clientes!A2:A151) -> 150
A4: Clientes Activos | B4: =COUNTIF(Clientes!K2:K151,"Activo") -> 102
A5: Clientes En riesgo | B5: =COUNTIF(Clientes!K2:K151,"En riesgo") -> 27
A6: Clientes Suspendidos | B6: =COUNTIF(Clientes!K2:K151,"Suspendido") -> 21
A8: Ventas totales 2024 (COP) | B8: =SUM(Clientes!E2:E151) -> 11061500000
A9: Ingresos totales 2025 (COP) | B9: =SUM(Clientes!G2:G151) -> 12973355990
A10: Crecimiento total 2024→2025 | B10: =B9/B8-1 -> 0.17283876
A12: Cartera vencida total (COP) | B12: =SUM(Clientes!I2:I151) -> 761274180
A13: Cartera vencida / Ventas 2024 | B13: =B12/B8 -> 0.068821966
A14: Cartera en riesgo (clientes En riesgo + Suspendido) (COP) | B14: =SUMIFS(Clientes!I2:I151,Clientes!K2:K151,"En riesgo")+SUMIFS(Clientes!I2:I151,Clientes!K2:K151,"Suspendido") -> 469885170
A16: Clientes grandes (>$50M ventas 2024) | B16: =COUNTIF(Clientes!E2:E151,">50000000") -> 75
A17: Clientes medianos ($10M-$50M) | B17: =COUNTIFS(Clientes!E2:E151,">=10000000",Clientes!E2:E151,"<=50000000") -> 45
A18: Clientes pequeños (<$10M) | B18: =COUNTIF(Clientes!E2:E151,"<10000000") -> 30
A20: Días de pago promedio (todos) | B20: =AVERAGE(Clientes!J2:J151) -> 37.3
A22: Top 10 Clientes por Ingresos 2025
A23: ID | B23: Nombre | C23: Ciudad | D23: Ingresos 2025 (COP)
A24: C023 | B24: Comedor Institucional San José | C24: Santa Marta | D24: =Clientes!G24 -> 227627600
A25: C078 | B25: Autoservicios La Riviera | C25: Cartagena | D25: =Clientes!G79 -> 225491600
A26: C016 | B26: Supermercado Ahorro Costeño | C26: Valledupar | D26: =Clientes!G17 -> 224081760
A27: C094 | B27: Hipermercado La Canasta | C27: Cartagena | D27: =Clientes!G95 -> 223772980
A28: C010 | B28: Supermercado La Economía | C28: Barranquilla | D28: =Clientes!G11 -> 222920100
A29: C116 | B29: Supermercado La Canasta | C29: Santa Marta | D29: =Clientes!G117 -> 220298400
A30: C150 | B30: Cafetería Empresarial San Fernando | C30: Cartagena | D30: =Clientes!G151 -> 219778680
A31: C047 | B31: Super Ahorro Costeño | C31: Cartagena | D31: =Clientes!G48 -> 219641520
A32: C119 | B32: Minimercado La Economía | C32: Cartagena | D32: =Clientes!G120 -> 218304500
A33: C001 | B33: Super Todo Fresco | C33: Valledupar | D33: =Clientes!G2 -> 216881840
A35: Nota: datos simulados con fines de demostración / analítica del programa Master IA Local. No corresponden a información real de clientes de Andina Foods S.A.S.
