Workbook

Sheet Politica_Beneficios
B2: POLÍTICA DE BENEFICIOS Y PRESTACIONES SOCIALES — ANDINA FOODS S.A.S.
B3: Documento de simulación — datos y cifras ficticias, con base en el marco legal laboral colombiano
B5: Descansos y jornada laboral
B6: • Jornada laboral: 47 horas semanales (Ley 2101 de 2021 — reducción gradual hasta 42 horas en 2026).
B7: • Descanso semanal remunerado: un (1) día, habitualmente el domingo.
B8: • Horas extra diurnas: recargo del 25%. Horas extra nocturnas: recargo del 75%.
B9: • Recargo nocturno (no extra): 35% sobre el valor de la hora ordinaria.
B10: • Recargo dominical/festivo: 75% adicional sobre el valor de la hora ordinaria.
B12: Vacaciones
B13: • 15 días hábiles remunerados por cada año de servicio (Art. 186 CST).
B14: • Se programan de común acuerdo entre el colaborador y su jefe directo, priorizando la operación.
B15: • No son acumulables por más de dos (2) años sin autorización de Talento Humano.
... B53: • Cuota mínima obligatoria según número de trabajadores, conforme a la Ley 789 de 2002.

Sheet Parametros_Legales
B2: PARÁMETROS LEGALES DE NÓMINA — COLOMBIA (cifras de referencia, uso en simulación)
B4: Concepto | C4: Valor | D4: Observación
B5: Salario Mínimo Legal Mensual Vigente (SMLMV) | C5: 1423500 | D5: COP/mes — referencia 2025
B6: Auxilio de Transporte | C6: 200000 | D6: COP/mes — aplica a quien gana ≤ 2 SMLMV
B7: Aporte Salud — Empleado | C7: 0.04 | D7: % del salario básico
B8: Aporte Salud — Empleador | C8: 0.085 | D8: % del salario básico (exonerado si el salario < 10 SMLMV, Ley 1819/2016)
B9: Aporte Pensión — Empleado | C9: 0.04 | D9: % del salario básico
B10: Aporte Pensión — Empleador | C10: 0.12 | D10: % del salario básico
B11: Fondo de Solidaridad Pensional | C11: 0.01 | D11: % adicional a empleados con salario ≥ 4 SMLMV (a cargo del empleado)
B12: Aporte Caja de Compensación Familiar | C12: 0.04 | D12: % del salario básico — a cargo del empleador (Cajacopi Atlántico)
B13: Aporte ICBF | C13: 0.03 | D13: % del salario básico — empleador (exonerado si salario < 10 SMLMV)
B14: Aporte SENA | C14: 0.02 | D14: % del salario básico — empleador (exonerado si salario < 10 SMLMV)
B15: Umbral de exoneración (10 SMLMV) | C15: 14235000 | D15: COP — por encima de este valor NO aplica exoneración de Ley 1819
B16: Cesantías | C16: 0.0833 | D16: 8.33% del salario mensual — un salario por año, a fondo de cesantías
... B20: Dotación (calzado y vestido de labor) | C20: 3 | D20: veces al año — para quienes ganan ≤ 2 SMLMV (Código Sustantivo del Trabajo)
B22: Clases de riesgo ARL aplicadas en esta empresa (Decreto 1607 de 2002):
B23: Clase de riesgo | C23: Aplica a
B24: Clase I (0.522%) | C24: Personal administrativo, comercial y directivo (oficinas)
B25: Clase III (2.436%) | C25: Auxiliares de bodega, montacarguistas, mercaderistas
B26: Clase IV (4.350%) | C26: Conductores y auxiliares de reparto
B27: Clase V (6.960%) | C27: Personal de seguridad

Sheet Resumen_por_Cargo
B2: RESUMEN DE NÓMINA POR CARGO — DISTRIBUIDORA ANDINA FOODS S.A.S. (datos ficticios)
B4: Cargo | C4: Departamento | D4: N° empleados | E4: Salario básico promedio | F4: Salario básico mínimo | G4: Salario básico máximo | H4: Costo total empleador (mes)
B5: Gerente General (CEO) | C5: Dirección General | D5: =COUNTIF(Nomina_Detallada!$D$2:$D$188,B5) -> 1 | E5: =AVERAGEIF(Nomina_Detallada!$D$2:$D$188,B5,Nomina_Detallada!$K$2:$K$188) -> 35000000 | F5: =_xlfn.MINIFS(Nomina_Detallada!$K$2:$K$188,Nomina_Detallada!$D$2:$D$188,B5) -> 35000000 | G5: =_xlfn.MAXIFS(Nomina_Detallada!$K$2:$K$188,Nomina_Detallada!$D$2:$D$188,B5) -> 35000000 | H5: =SUMIF(Nomina_Detallada!$D$2:$D$188,B5,Nomina_Detallada!$W$2:$W$188) -> 50865500
B6: Gerente Financiero y Administrativo | C6: Financiero y Administrativo | D6: =COUNTIF(Nomina_Detallada!$D$2:$D$188,B6) -> 1 | E6: =AVERAGEIF(Nomina_Detallada!$D$2:$D$188,B6,Nomina_Detallada!$K$2:$K$188) -> 19000000 | F6: =_xlfn.MINIFS(Nomina_Detallada!$K$2:$K$188,Nomina_Detallada!$D$2:$D$188,B6) -> 19000000 | G6: =_xlfn.MAXIFS(Nomina_Detallada!$K$2:$K$188,Nomina_Detallada!$D$2:$D$188,B6) -> 19000000 | H6: =SUMIF(Nomina_Detallada!$D$2:$D$188,B6,Nomina_Detallada!$W$2:$W$188) -> 27612700
B7: Gerente Comercial y de Ventas | C7: Comercial y Ventas | D7: =COUNTIF(Nomina_Detallada!$D$2:$D$188,B7) -> 1 | E7: =AVERAGEIF(Nomina_Detallada!$D$2:$D$188,B7,Nomina_Detallada!$K$2:$K$188) -> 19500000 | F7: =_xlfn.MINIFS(Nomina_Detallada!$K$2:$K$188,Nomina_Detallada!$D$2:$D$188,B7) -> 19500000 | G7: =_xlfn.MAXIFS(Nomina_Detallada!$K$2:$K$188,Nomina_Detallada!$D$2:$D$188,B7) -> 19500000 | H7: =SUMIF(Nomina_Detallada!$D$2:$D$188,B7,Nomina_Detallada!$W$2:$W$188) -> 28339350
B8: Gerente de Operaciones y Logística | C8: Operaciones y Logística | D8: =COUNTIF(Nomina_Detallada!$D$2:$D$188,B8) -> 1 | E8: =AVERAGEIF(Nomina_Detallada!$D$2:$D$188,B8,Nomina_Detallada!$K$2:$K$188) -> 18500000 | F8: =_xlfn.MINIFS(Nomina_Detallada!$K$2:$K$188,Nomina_Detallada!$D$2:$D$188,B8) -> 18500000 | G8: =_xlfn.MAXIFS(Nomina_Detallada!$K$2:$K$188,Nomina_Detallada!$D$2:$D$188,B8) -> 18500000 | H8: =SUMIF(Nomina_Detallada!$D$2:$D$188,B8,Nomina_Detallada!$W$2:$W$188) -> 26886050
B9: Gerente de Talento Humano | C9: Talento Humano | D9: =COUNTIF(Nomina_Detallada!$D$2:$D$188,B9) -> 1 | E9: =AVERAGEIF(Nomina_Detallada!$D$2:$D$188,B9,Nomina_Detallada!$K$2:$K$188) -> 16500000 | F9: =_xlfn.MINIFS(Nomina_Detallada!$K$2:$K$188,Nomina_Detallada!$D$2:$D$188,B9) -> 16500000 | G9: =_xlfn.MAXIFS(Nomina_Detallada!$K$2:$K$188,Nomina_Detallada!$D$2:$D$188,B9) -> 16500000 | H9: =SUMIF(Nomina_Detallada!$D$2:$D$188,B9,Nomina_Detallada!$W$2:$W$188) -> 23979450
B10: Jefe de Tecnología (TI) | C10: Tecnología | D10: =COUNTIF(Nomina_Detallada!$D$2:$D$188,B10) -> 1 | E10: =AVERAGEIF(Nomina_Detallada!$D$2:$D$188,B10,Nomina_Detallada!$K$2:$K$188) -> 9800000 | F10: =_xlfn.MINIFS(Nomina_Detallada!$K$2:$K$188,Nomina_Detallada!$D$2:$D$188,B10) -> 9800000 | G10: =_xlfn.MAXIFS(Nomina_Detallada!$K$2:$K$188,Nomina_Detallada!$D$2:$D$188,B10) -> 9800000 | H10: =SUMIF(Nomina_Detallada!$D$2:$D$188,B10,Nomina_Detallada!$W$2:$W$188) -> 13409340
B11: Jefe de Ventas Canal Tradicional | C11: Comercial y Ventas | D11: =COUNTIF(Nomina_Detallada!$D$2:$D$188,B11) -> 1 | E11: =AVERAGEIF(Nomina_Detallada!$D$2:$D$188,B11,Nomina_Detallada!$K$2:$K$188) -> 6800000 | F11: =_xlfn.MINIFS(Nomina_Detallada!$K$2:$K$188,Nomina_Detallada!$D$2:$D$188,B11) -> 6800000 | G11: =_xlfn.MAXIFS(Nomina_Detallada!$K$2:$K$188,Nomina_Detallada!$D$2:$D$188,B11) -> 6800000 | H11: =SUMIF(Nomina_Detallada!$D$2:$D$188,B11,Nomina_Detallada!$W$2:$W$188) -> 9304440
B12: Jefe de Ventas Canal Moderno/Institucional | C12: Comercial y Ventas | D12: =COUNTIF(Nomina_Detallada!$D$2:$D$188,B12) -> 1 | E12: =AVERAGEIF(Nomina_Detallada!$D$2:$D$188,B12,Nomina_Detallada!$K$2:$K$188) -> 7000000 | F12: =_xlfn.MINIFS(Nomina_Detallada!$K$2:$K$188,Nomina_Detallada!$D$2:$D$188,B12) -> 7000000 | G12: =_xlfn.MAXIFS(Nomina_Detallada!$K$2:$K$188,Nomina_Detallada!$D$2:$D$188,B12) -> 7000000 | H12: =SUMIF(Nomina_Detallada!$D$2:$D$188,B12,Nomina_Detallada!$W$2:$W$188) -> 9578100
B13: Coordinador de Trade Marketing | C13: Comercial y Ventas | D13: =COUNTIF(Nomina_Detallada!$D$2:$D$188,B13) -> 1 | E13: =AVERAGEIF(Nomina_Detallada!$D$2:$D$188,B13,Nomina_Detallada!$K$2:$K$188) -> 5600000 | F13: =_xlfn.MINIFS(Nomina_Detallada!$K$2:$K$188,Nomina_Detallada!$D$2:$D$188,B13) -> 5600000 | G13: =_xlfn.MAXIFS(Nomina_Detallada!$K$2:$K$188,Nomina_Detallada!$D$2:$D$188,B13) -> 5600000 | H13: =SUMIF(Nomina_Detallada!$D$2:$D$188,B13,Nomina_Detallada!$W$2:$W$188) -> 7662480
B14: Jefe de Bodega y Almacenamiento | C14: Operaciones y Logística | D14: =COUNTIF(Nomina_Detallada!$D$2:$D$188,B14) -> 1 | E14: =AVERAGEIF(Nomina_Detallada!$D$2:$D$188,B14,Nomina_Detallada!$K$2:$K$188) -> 6200000 | F14: =_xlfn.MINIFS(Nomina_Detallada!$K$2:$K$188,Nomina_Detallada!$D$2:$D$188,B14) -> 6200000 | G14: =_xlfn.MAXIFS(Nomina_Detallada!$K$2:$K$188,Nomina_Detallada!$D$2:$D$188,B14) -> 6200000 | H14: =SUMIF(Nomina_Detallada!$D$2:$D$188,B14,Nomina_Detallada!$W$2:$W$188) -> 8483460
B15: Jefe de Flota y Distribución | C15: Operaciones y Logística | D15: =COUNTIF(Nomina_Detallada!$D$2:$D$188,B15) -> 1 | E15: =AVERAGEIF(Nomina_Detallada!$D$2:$D$188,B15,Nomina_Detallada!$K$2:$K$188) -> 6400000 | F15: =_xlfn.MINIFS(Nomina_Detallada!$K$2:$K$188,Nomina_Detallada!$D$2:$D$188,B15) -> 6400000 | G15: =_xlfn.MAXIFS(Nomina_Detallada!$K$2:$K$188,Nomina_Detallada!$D$2:$D$188,B15) -> 6400000 | H15: =SUMIF(Nomina_Detallada!$D$2:$D$188,B15,Nomina_Detallada!$W$2:$W$188) -> 8757120
B16: Coordinador de Compras y Abastecimiento | C16: Operaciones y Logística | D16: =COUNTIF(Nomina_Detallada!$D$2:$D$188,B16) -> 1 | E16: =AVERAGEIF(Nomina_Detallada!$D$2:$D$188,B16,Nomina_Detallada!$K$2:$K$188) -> 5800000 | F16: =_xlfn.MINIFS(Nomina_Detallada!$K$2:$K$188,Nomina_Detallada!$D$2:$D$188,B16) -> 5800000 | G16: =_xlfn.MAXIFS(Nomina_Detallada!$K$2:$K$188,Nomina_Detallada!$D$2:$D$188,B16) -> 5800000 | H16: =SUMIF(Nomina_Detallada!$D$2:$D$188,B16,Nomina_Detallada!$W$2:$W$188) -> 7936140
... B31: Aprendiz SENA (etapa práctica) | C31: Talento Humano | D31: =COUNTIF(Nomina_Detallada!$D$2:$D$188,B31) -> 7 | E31: =AVERAGEIF(Nomina_Detallada!$D$2:$D$188,B31,Nomina_Detallada!$K$2:$K$188) -> 1067625 | F31: =_xlfn.MINIFS(Nomina_Detallada!$K$2:$K$188,Nomina_Detallada!$D$2:$D$188,B31) -> 1067625 | G31: =_xlfn.MAXIFS(Nomina_Detallada!$K$2:$K$188,Nomina_Detallada!$D$2:$D$188,B31) -> 1067625 | H31: =SUMIF(Nomina_Detallada!$D$2:$D$188,B31,Nomina_Detallada!$W$2:$W$188) -> 11625819
B33: TOTAL EMPRESA | D33: =SUM(D5:D31) -> 187 | H33: =SUM(H5:H31) -> 7.1334634e+08

Sheet Nomina_Detallada
A1: No. | B1: Cédula | C1: Nombre completo | D1: Cargo | E1: Departamento | F1: Tipo de contrato | G1: Fecha de ingreso | H1: ARL (clase) | I1: EPS | J1: Fondo de Pensión (AFP) | K1: Salario básico | L1: Auxilio de transporte | M1: Salud (empleado) | N1: Pensión (empleado) | O1: Total deducciones | P1: Neto a pagar (mes) | Q1: Salud (empleador) | R1: Pensión (empleador) | S1: Caja de Compensación | T1: Cesantías (mensual) | U1: Prima (mensual) | V1: Vacaciones (mensual) | W1: Costo total empleador (mes)
A2: 1 | B2: 1029885207 | C2: Carlos Andrés Meléndez Ruiz | D2: Gerente General (CEO) | E2: Dirección General | F2: Indefinido | G2: 41284 | H2: I | I2: Nueva EPS | J2: Porvenir | K2: 35000000 | L2: =IF(K2<=2*Parametros_Legales!$C$5,Parametros_Legales!$C$6,0) -> 0 | M2: =K2*Parametros_Legales!$C$7 -> 1400000 | N2: =K2*(Parametros_Legales!$C$9+IF(K2>=4*Parametros_Legales!$C$5,Parametros_Legales!$C$11,0)) -> 1750000 | O2: =M2+N2 -> 3150000 | P2: =K2+L2-O2 -> 31850000 | Q2: =IF(K2<Parametros_Legales!$C$15,0,K2*Parametros_Legales!$C$8) -> 2975000 | R2: =K2*Parametros_Legales!$C$10 -> 4200000 | S2: =K2*Parametros_Legales!$C$12 -> 1400000 | T2: =K2*Parametros_Legales!$C$16 -> 2915500 | U2: =K2*Parametros_Legales!$C$18 -> 2915500 | V2: =K2*Parametros_Legales!$C$19 -> 1459500 | W2: =K2+L2+Q2+R2+S2+T2+U2+V2 -> 50865500
A3: 2 | B3: 1199058447 | C3: Diana Patricia Osorio Cantillo | D3: Gerente Financiero y Administrativo | E3: Financiero y Administrativo | F3: Indefinido | G3: 43272 | H3: I | I3: Salud Total | J3: Colpensiones | K3: 19000000 | L3: =IF(K3<=2*Parametros_Legales!$C$5,Parametros_Legales!$C$6,0) -> 0 | M3: =K3*Parametros_Legales!$C$7 -> 760000 | N3: =K3*(Parametros_Legales!$C$9+IF(K3>=4*Parametros_Legales!$C$5,Parametros_Legales!$C$11,0)) -> 950000 | O3: =M3+N3 -> 1710000 | P3: =K3+L3-O3 -> 17290000 | Q3: =IF(K3<Parametros_Legales!$C$15,0,K3*Parametros_Legales!$C$8) -> 1615000 | R3: =K3*Parametros_Legales!$C$10 -> 2280000 | S3: =K3*Parametros_Legales!$C$12 -> 760000 | T3: =K3*Parametros_Legales!$C$16 -> 1582700 | U3: =K3*Parametros_Legales!$C$18 -> 1582700 | V3: =K3*Parametros_Legales!$C$19 -> 792300 | W3: =K3+L3+Q3+R3+S3+T3+U3+V3 -> 27612700
A4: 3 | B4: 1065737657 | C4: Jorge Luis Herrera Barros | D4: Gerente Comercial y de Ventas | E4: Comercial y Ventas | F4: Indefinido | G4: 43490 | H4: I | I4: Mutual SER | J4: Colfondos | K4: 19500000 | L4: =IF(K4<=2*Parametros_Legales!$C$5,Parametros_Legales!$C$6,0) -> 0 | M4: =K4*Parametros_Legales!$C$7 -> 780000 | N4: =K4*(Parametros_Legales!$C$9+IF(K4>=4*Parametros_Legales!$C$5,Parametros_Legales!$C$11,0)) -> 975000 | O4: =M4+N4 -> 1755000 | P4: =K4+L4-O4 -> 17745000 | Q4: =IF(K4<Parametros_Legales!$C$15,0,K4*Parametros_Legales!$C$8) -> 1657500 | R4: =K4*Parametros_Legales!$C$10 -> 2340000 | S4: =K4*Parametros_Legales!$C$12 -> 780000 | T4: =K4*Parametros_Legales!$C$16 -> 1624350 | U4: =K4*Parametros_Legales!$C$18 -> 1624350 | V4: =K4*Parametros_Legales!$C$19 -> 813150 | W4: =K4+L4+Q4+R4+S4+T4+U4+V4 -> 28339350
A5: 4 | B5: 1037456926 | C5: Marcela Isabel Torres Pacheco | D5: Gerente de Operaciones y Logística | E5: Operaciones y Logística | F5: Indefinido | G5: 43231 | H5: I | I5: Coomeva EPS | J5: Protección | K5: 18500000 | L5: =IF(K5<=2*Parametros_Legales!$C$5,Parametros_Legales!$C$6,0) -> 0 | M5: =K5*Parametros_Legales!$C$7 -> 740000 | N5: =K5*(Parametros_Legales!$C$9+IF(K5>=4*Parametros_Legales!$C$5,Parametros_Legales!$C$11,0)) -> 925000 | O5: =M5+N5 -> 1665000 | P5: =K5+L5-O5 -> 16835000 | Q5: =IF(K5<Parametros_Legales!$C$15,0,K5*Parametros_Legales!$C$8) -> 1572500 | R5: =K5*Parametros_Legales!$C$10 -> 2220000 | S5: =K5*Parametros_Legales!$C$12 -> 740000 | T5: =K5*Parametros_Legales!$C$16 -> 1541050 | U5: =K5*Parametros_Legales!$C$18 -> 1541050 | V5: =K5*Parametros_Legales!$C$19 -> 771450 | W5: =K5+L5+Q5+R5+S5+T5+U5+V5 -> 26886050
A6: 5 | B6: 1181650134 | C6: Andrés Felipe Cárdenas Molina | D6: Gerente de Talento Humano | E6: Talento Humano | F6: Indefinido | G6: 44209 | H6: I | I6: Sura EPS | J6: Porvenir | K6: 16500000 | L6: =IF(K6<=2*Parametros_Legales!$C$5,Parametros_Legales!$C$6,0) -> 0 | M6: =K6*Parametros_Legales!$C$7 -> 660000 | N6: =K6*(Parametros_Legales!$C$9+IF(K6>=4*Parametros_Legales!$C$5,Parametros_Legales!$C$11,0)) -> 825000 | O6: =M6+N6 -> 1485000 | P6: =K6+L6-O6 -> 15015000 | Q6: =IF(K6<Parametros_Legales!$C$15,0,K6*Parametros_Legales!$C$8) -> 1402500 | R6: =K6*Parametros_Legales!$C$10 -> 1980000 | S6: =K6*Parametros_Legales!$C$12 -> 660000 | T6: =K6*Parametros_Legales!$C$16 -> 1374450 | U6: =K6*Parametros_Legales!$C$18 -> 1374450 | V6: =K6*Parametros_Legales!$C$19 -> 688050 | W6: =K6+L6+Q6+R6+S6+T6+U6+V6 -> 23979450
A7: 6 | B7: 1023337464 | C7: Laura Sofía Restrepo Vega | D7: Jefe de Tecnología (TI) | E7: Tecnología | F7: Indefinido | G7: 44032 | H7: I | I7: Nueva EPS | J7: Colpensiones | K7: 9800000 | L7: =IF(K7<=2*Parametros_Legales!$C$5,Parametros_Legales!$C$6,0) -> 0 | M7: =K7*Parametros_Legales!$C$7 -> 392000 | N7: =K7*(Parametros_Legales!$C$9+IF(K7>=4*Parametros_Legales!$C$5,Parametros_Legales!$C$11,0)) -> 490000 | O7: =M7+N7 -> 882000 | P7: =K7+L7-O7 -> 8918000 | Q7: =IF(K7<Parametros_Legales!$C$15,0,K7*Parametros_Legales!$C$8) -> 0 | R7: =K7*Parametros_Legales!$C$10 -> 1176000 | S7: =K7*Parametros_Legales!$C$12 -> 392000 | T7: =K7*Parametros_Legales!$C$16 -> 816340 | U7: =K7*Parametros_Legales!$C$18 -> 816340 | V7: =K7*Parametros_Legales!$C$19 -> 408660 | W7: =K7+L7+Q7+R7+S7+T7+U7+V7 -> 13409340
A8: 7 | B8: 1113258777 | C8: Ana María Salcedo Iguarán | D8: Jefe de Ventas Canal Tradicional | E8: Comercial y Ventas | F8: Indefinido | G8: 43574 | H8: I | I8: Salud Total | J8: Colfondos | K8: 6800000 | L8: =IF(K8<=2*Parametros_Legales!$C$5,Parametros_Legales!$C$6,0) -> 0 | M8: =K8*Parametros_Legales!$C$7 -> 272000 | N8: =K8*(Parametros_Legales!$C$9+IF(K8>=4*Parametros_Legales!$C$5,Parametros_Legales!$C$11,0)) -> 340000 | O8: =M8+N8 -> 612000 | P8: =K8+L8-O8 -> 6188000 | Q8: =IF(K8<Parametros_Legales!$C$15,0,K8*Parametros_Legales!$C$8) -> 0 | R8: =K8*Parametros_Legales!$C$10 -> 816000 | S8: =K8*Parametros_Legales!$C$12 -> 272000 | T8: =K8*Parametros_Legales!$C$16 -> 566440 | U8: =K8*Parametros_Legales!$C$18 -> 566440 | V8: =K8*Parametros_Legales!$C$19 -> 283560 | W8: =K8+L8+Q8+R8+S8+T8+U8+V8 -> 9304440
A9: 8 | B9: 1007998630 | C9: Rodrigo Enrique Blanco Cervantes | D9: Jefe de Ventas Canal Moderno/Institucional | E9: Comercial y Ventas | F9: Indefinido | G9: 45083 | H9: I | I9: Mutual SER | J9: Protección | K9: 7000000 | L9: =IF(K9<=2*Parametros_Legales!$C$5,Parametros_Legales!$C$6,0) -> 0 | M9: =K9*Parametros_Legales!$C$7 -> 280000 | N9: =K9*(Parametros_Legales!$C$9+IF(K9>=4*Parametros_Legales!$C$5,Parametros_Legales!$C$11,0)) -> 350000 | O9: =M9+N9 -> 630000 | P9: =K9+L9-O9 -> 6370000 | Q9: =IF(K9<Parametros_Legales!$C$15,0,K9*Parametros_Legales!$C$8) -> 0 | R9: =K9*Parametros_Legales!$C$10 -> 840000 | S9: =K9*Parametros_Legales!$C$12 -> 280000 | T9: =K9*Parametros_Legales!$C$16 -> 583100 | U9: =K9*Parametros_Legales!$C$18 -> 583100 | V9: =K9*Parametros_Legales!$C$19 -> 291900 | W9: =K9+L9+Q9+R9+S9+T9+U9+V9 -> 9578100
A10: 9 | B10: 1058690184 | C10: Katherine Julissa Noriega Amaya | D10: Coordinador de Trade Marketing | E10: Comercial y Ventas | F10: Indefinido | G10: 45322 | H10: I | I10: Coomeva EPS | J10: Porvenir | K10: 5600000 | L10: =IF(K10<=2*Parametros_Legales!$C$5,Parametros_Legales!$C$6,0) -> 0 | M10: =K10*Parametros_Legales!$C$7 -> 224000 | N10: =K10*(Parametros_Legales!$C$9+IF(K10>=4*Parametros_Legales!$C$5,Parametros_Legales!$C$11,0)) -> 224000 | O10: =M10+N10 -> 448000 | P10: =K10+L10-O10 -> 5152000 | Q10: =IF(K10<Parametros_Legales!$C$15,0,K10*Parametros_Legales!$C$8) -> 0 | R10: =K10*Parametros_Legales!$C$10 -> 672000 | S10: =K10*Parametros_Legales!$C$12 -> 224000 | T10: =K10*Parametros_Legales!$C$16 -> 466480 | U10: =K10*Parametros_Legales!$C$18 -> 466480 | V10: =K10*Parametros_Legales!$C$19 -> 233520 | W10: =K10+L10+Q10+R10+S10+T10+U10+V10 -> 7662480
A11: 10 | B11: 1135655277 | C11: Hernán Darío Fontalvo Redondo | D11: Jefe de Bodega y Almacenamiento | E11: Operaciones y Logística | F11: Indefinido | G11: 44307 | H11: III | I11: Sura EPS | J11: Colpensiones | K11: 6200000 | L11: =IF(K11<=2*Parametros_Legales!$C$5,Parametros_Legales!$C$6,0) -> 0 | M11: =K11*Parametros_Legales!$C$7 -> 248000 | N11: =K11*(Parametros_Legales!$C$9+IF(K11>=4*Parametros_Legales!$C$5,Parametros_Legales!$C$11,0)) -> 310000 | O11: =M11+N11 -> 558000 | P11: =K11+L11-O11 -> 5642000 | Q11: =IF(K11<Parametros_Legales!$C$15,0,K11*Parametros_Legales!$C$8) -> 0 | R11: =K11*Parametros_Legales!$C$10 -> 744000 | S11: =K11*Parametros_Legales!$C$12 -> 248000 | T11: =K11*Parametros_Legales!$C$16 -> 516460 | U11: =K11*Parametros_Legales!$C$18 -> 516460 | V11: =K11*Parametros_Legales!$C$19 -> 258540 | W11: =K11+L11+Q11+R11+S11+T11+U11+V11 -> 8483460
A12: 11 | B12: 1007123195 | C12: Iván Mauricio Charris Barrios | D12: Jefe de Flota y Distribución | E12: Operaciones y Logística | F12: Indefinido | G12: 43916 | H12: IV | I12: Nueva EPS | J12: Colfondos | K12: 6400000 | L12: =IF(K12<=2*Parametros_Legales!$C$5,Parametros_Legales!$C$6,0) -> 0 | M12: =K12*Parametros_Legales!$C$7 -> 256000 | N12: =K12*(Parametros_Legales!$C$9+IF(K12>=4*Parametros_Legales!$C$5,Parametros_Legales!$C$11,0)) -> 320000 | O12: =M12+N12 -> 576000 | P12: =K12+L12-O12 -> 5824000 | Q12: =IF(K12<Parametros_Legales!$C$15,0,K12*Parametros_Legales!$C$8) -> 0 | R12: =K12*Parametros_Legales!$C$10 -> 768000 | S12: =K12*Parametros_Legales!$C$12 -> 256000 | T12: =K12*Parametros_Legales!$C$16 -> 533120 | U12: =K12*Parametros_Legales!$C$18 -> 533120 | V12: =K12*Parametros_Legales!$C$19 -> 266880 | W12: =K12+L12+Q12+R12+S12+T12+U12+V12 -> 8757120
A13: 12 | B13: 1053375074 | C13: Silvia Johana Deluque Pinedo | D13: Coordinador de Compras y Abastecimiento | E13: Operaciones y Logística | F13: Indefinido | G13: 44364 | H13: I | I13: Salud Total | J13: Protección | K13: 5800000 | L13: =IF(K13<=2*Parametros_Legales!$C$5,Parametros_Legales!$C$6,0) -> 0 | M13: =K13*Parametros_Legales!$C$7 -> 232000 | N13: =K13*(Parametros_Legales!$C$9+IF(K13>=4*Parametros_Legales!$C$5,Parametros_Legales!$C$11,0)) -> 290000 | O13: =M13+N13 -> 522000 | P13: =K13+L13-O13 -> 5278000 | Q13: =IF(K13<Parametros_Legales!$C$15,0,K13*Parametros_Legales!$C$8) -> 0 | R13: =K13*Parametros_Legales!$C$10 -> 696000 | S13: =K13*Parametros_Legales!$C$12 -> 232000 | T13: =K13*Parametros_Legales!$C$16 -> 483140 | U13: =K13*Parametros_Legales!$C$18 -> 483140 | V13: =K13*Parametros_Legales!$C$19 -> 241860 | W13: =K13+L13+Q13+R13+S13+T13+U13+V13 -> 7936140
... A188: 187 | B188: 1174439199 | C188: Carolina Pinedo Cantillo | D188: Aprendiz SENA (etapa práctica) | E188: Talento Humano | F188: Aprendizaje | G188: 46040 | H188: I | I188: Salud Total | J188: N/A (aprendiz) | K188: 1067625 | L188: =IF(K188<=2*Parametros_Legales!$C$5,Parametros_Legales!$C$6,0) -> 200000 | M188: =K188*Parametros_Legales!$C$7 -> 42705 | N188: =K188*(Parametros_Legales!$C$9+IF(K188>=4*Parametros_Legales!$C$5,Parametros_Legales!$C$11,0)) -> 42705 | O188: =M188+N188 -> 85410 | P188: =K188+L188-O188 -> 1182215 | Q188: =IF(K188<Parametros_Legales!$C$15,0,K188*Parametros_Legales!$C$8) -> 0 | R188: =K188*Parametros_Legales!$C$10 -> 128115 | S188: =K188*Parametros_Legales!$C$12 -> 42705 | T188: =K188*Parametros_Legales!$C$16 -> 88933.163 | U188: =K188*Parametros_Legales!$C$18 -> 88933.163 | V188: =K188*Parametros_Legales!$C$19 -> 44519.963 | W188: =K188+L188+Q188+R188+S188+T188+U188+V188 -> 1660831.3
J189: TOTAL / PROMEDIO | K189: =SUM(K2:K188) -> 492526375 | L189: =SUM(L2:L188) -> 30200000 | M189: =SUM(M2:M188) -> 19701055 | N189: =SUM(N2:N188) -> 21263055 | O189: =SUM(O2:O188) -> 40964110 | P189: =SUM(P2:P188) -> 481762265 | Q189: =SUM(Q2:Q188) -> 9222500 | R189: =SUM(R2:R188) -> 59103165 | ... W189: =SUM(W2:W188) -> 7.1334634e+08
