Workbook

Sheet Detalle
A1: ID | B1: Fecha Registro | C1: Tipo | D1: Categoría | E1: Cliente/Interno | F1: Descripción | G1: Departamento Responsable | H1: Prioridad | I1: Estado | J1: Causa Raíz | K1: Acción Correctiva | L1: Fecha Resolución | M1: Días para Resolver | N1: Costo Impacto (COP) | O1: Seguimiento
A2: PQRS-001 | B2: 45660 | C2: Reclamo | D2: Entrega/Logística | E2: Tienda El Trebol | F2: Los empaques llegaron golpeados por mal manejo durante el transporte. | G2: Logística y Distribución | H2: Alta | I2: Resuelto | J2: Ruta de reparto mal planificada para la zona. | K2: Se reenvió el faltante en un despacho adicional sin costo. | L2: 45689 | M2: =IF(L2="","",L2-B2) -> 29 | N2: 1939000 | O2: Sí
A3: PQRS-002 | B3: 45665 | C3: Petición | D3: Facturación | E3: Panadería San Fernando | F3: La factura tiene un valor distinto al acordado en el pedido. | G3: Finanzas y Contabilidad | H3: Crítica | I3: Abierto | M3: =IF(L3="","",L3-B3) | N3: 0 | O3: Sí
A4: PQRS-003 | B4: 45668 | C4: Sugerencia | D4: Entrega/Logística | E4: Deposito San Roque | F4: Se solicita ampliar la frecuencia de reparto para la zona. | G4: Logística y Distribución | H4: Baja | I4: En proceso | M4: =IF(L4="","",L4-B4) | N4: 0 | O4: Sí
A5: PQRS-004 | B5: 45670 | C5: Queja | D5: Entrega/Logística | E5: Supermercado Ahorro Costeño | F5: Los empaques llegaron golpeados por mal manejo durante el transporte. | G5: Logística y Distribución | H5: Alta | I5: Resuelto | J5: Error en el alistamiento de pedido en bodega. | K5: Se reasignó la ruta y se coordinó nuevo horario con el cliente. | L5: 45698 | M5: =IF(L5="","",L5-B5) -> 28 | N5: 1122000 | O5: Sí
A6: PQRS-005 | B6: 45676 | C6: Reclamo | D6: Facturación | E6: Hospital Del Caribe | F6: El cliente no ha recibido la factura electrónica del pedido. | G6: Finanzas y Contabilidad | H6: Media | I6: En proceso | J6: Falla en el envío automático de la factura electrónica. | M6: =IF(L6="","",L6-B6) | N6: 0 | O6: Sí
A7: PQRS-006 | B7: 45677 | C7: Reclamo | D7: Calidad producto | E7: Tienda El Faro | F7: El cliente reporta sabor o textura distinta a la habitual del producto. | G7: Bodega y Almacén | H7: Alta | I7: Resuelto | J7: Condiciones de almacenamiento inadecuadas (humedad/temperatura). | K7: Se ajustaron las condiciones de almacenamiento en la bodega regional. | L7: 45683 | M7: =IF(L7="","",L7-B7) -> 6 | N7: 0 | O7: Sí
A8: PQRS-007 | B8: 45677 | C8: Sugerencia | D8: Servicio | E8: Autoservicios La Bonanza | F8: El cliente solicita más información sobre el catálogo de productos. | G8: Servicio al Cliente | H8: Baja | I8: Resuelto | L8: 45703 | M8: =IF(L8="","",L8-B8) -> 26 | N8: 0 | O8: Sí
A9: PQRS-008 | B9: 45679 | C9: Petición | D9: Entrega/Logística | E9: Casino La Sagrada Familia | F9: El pedido llegó incompleto; faltaron varias referencias de la orden. | G9: Logística y Distribución | H9: Baja | I9: Resuelto | L9: 45691 | M9: =IF(L9="","",L9-B9) -> 12 | N9: 0 | O9: Sí
A10: PQRS-009 | B10: 45685 | C10: Sugerencia | D10: Calidad producto | E10: Supermercado La Economía | F10: El producto llegó próximo a su fecha de vencimiento. | G10: Bodega y Almacén | H10: Alta | I10: Resuelto | L10: 45693 | M10: =IF(L10="","",L10-B10) -> 8 | N10: 0 | O10: Sí
A11: PQRS-010 | B11: 45686 | C11: Petición | D11: Entrega/Logística | E11: Hipermercado La 15 | F11: El pedido llegó incompleto; faltaron varias referencias de la orden. | G11: Logística y Distribución | H11: Baja | I11: Resuelto | L11: 45711 | M11: =IF(L11="","",L11-B11) -> 25 | N11: 0 | O11: Sí
A12: PQRS-011 | B12: 45686 | C12: Reclamo | D12: Entrega/Logística | E12: Autoservicio Don Pedro | F12: La entrega llegó con más de 3 días de retraso frente a lo acordado. | G12: Logística y Distribución | H12: Alta | I12: Resuelto | J12: Congestión vial no prevista en la planeación de ruta. | K12: Se realizó reposición del producto dañado y se ajustó el embalaje. | L12: 45706 | M12: =IF(L12="","",L12-B12) -> 20 | N12: 781000 | O12: Sí
A13: PQRS-012 | B13: 45689 | C13: Queja | D13: Entrega/Logística | E13: Fundación La Sagrada Familia | F13: La entrega llegó con más de 3 días de retraso frente a lo acordado. | G13: Logística y Distribución | H13: Media | I13: En proceso | J13: Congestión vial no prevista en la planeación de ruta. | M13: =IF(L13="","",L13-B13) | N13: 2423000 | O13: Sí
A14: PQRS-013 | B14: 45689 | C14: Petición | D14: Entrega/Logística | E14: Minimercado Don Pedro | F14: Los empaques llegaron golpeados por mal manejo durante el transporte. | G14: Logística y Distribución | H14: Baja | I14: Cerrado | L14: 45713 | M14: =IF(L14="","",L14-B14) -> 24 | N14: 0 | O14: Sí
A15: PQRS-014 | B15: 45692 | C15: Sugerencia | D15: Otra | E15: Hipermercado La 15 | F15: Solicitud de información sobre el proceso de vinculación como proveedor. | G15: Gerencia General | H15: Baja | I15: Cerrado | L15: 45703 | M15: =IF(L15="","",L15-B15) -> 11 | N15: 0 | O15: Sí
A16: PQRS-015 | B16: 45693 | C16: Petición | D16: Facturación | E16: Minimercado San Judas | F16: Se cobró un producto que no fue entregado. | G16: Finanzas y Contabilidad | H16: Baja | I16: Resuelto | L16: 45696 | M16: =IF(L16="","",L16-B16) -> 3 | N16: 0 | O16: Sí
A17: PQRS-016 | B17: 45694 | C17: Queja | D17: Otra | E17: Deposito Las Delicias | F17: Solicitud de visita comercial para evaluar nuevas líneas de producto. | G17: Gerencia General | H17: Media | I17: Resuelto | J17: Solicitud de información, no aplica causa raíz. | K17: Se brindó la información solicitada al cliente. | L17: 45708 | M17: =IF(L17="","",L17-B17) -> 14 | N17: 0 | O17: No
A18: PQRS-017 | B18: 45697 | C18: Queja | D18: Entrega/Logística | E18: Cafetería Empresarial La Popa | F18: El pedido llegó incompleto; faltaron varias referencias de la orden. | G18: Logística y Distribución | H18: Media | I18: En proceso | J18: Congestión vial no prevista en la planeación de ruta. | M18: =IF(L18="","",L18-B18) | N18: 366000 | O18: Sí
A19: PQRS-018 | B19: 45704 | C19: Queja | D19: Entrega/Logística | E19: Autoservicio La Costeña | F19: Los empaques llegaron golpeados por mal manejo durante el transporte. | G19: Logística y Distribución | H19: Alta | I19: En proceso | J19: Personal de reparto nuevo sin inducción completa. | M19: =IF(L19="","",L19-B19) | N19: 2451000 | O19: Sí
A20: PQRS-019 | B20: 45704 | C20: Reclamo | D20: Entrega/Logística | E20: Clínica Nuestra Señora del Carmen | F20: El vehículo de reparto llegó fuera del horario pactado con la tienda. | G20: Logística y Distribución | H20: Alta | I20: Resuelto | J20: Ruta de reparto mal planificada para la zona. | K20: Se reforzó el checklist de alistamiento antes de despacho. | L20: 45721 | M20: =IF(L20="","",L20-B20) -> 17 | N20: 0 | O20: No
A21: PQRS-020 | B21: 45711 | C21: Queja | D21: Calidad producto | E21: Interno - Logística y Distribución | F21: Se identificó un lote con etiquetado incorrecto de fecha de vencimiento. | G21: Bodega y Almacén | H21: Crítica | I21: Resuelto | J21: Condiciones de almacenamiento inadecuadas (humedad/temperatura). | K21: Se cambió el producto y se reforzó la rotación FIFO en bodega. | L21: 45736 | M21: =IF(L21="","",L21-B21) -> 25 | N21: 1706000 | O21: No
A22: PQRS-021 | B22: 45712 | C22: Reclamo | D22: Calidad producto | E22: Autoservicios Mercar | F22: El producto llegó próximo a su fecha de vencimiento. | G22: Bodega y Almacén | H22: Alta | I22: Resuelto | J22: Condiciones de almacenamiento inadecuadas (humedad/temperatura). | K22: Se retiró el lote afectado y se notificó al proveedor. | L22: 45716 | M22: =IF(L22="","",L22-B22) -> 4 | N22: 0 | O22: No
A23: PQRS-022 | B23: 45712 | C23: Sugerencia | D23: Calidad producto | E23: Autoservicio La Costeña | F23: Se solicita revisar la calidad del último lote despachado. | G23: Bodega y Almacén | H23: Alta | I23: Resuelto | L23: 45735 | M23: =IF(L23="","",L23-B23) -> 23 | N23: 0 | O23: Sí
A24: PQRS-023 | B24: 45716 | C24: Reclamo | D24: Servicio | E24: Hipermercado El Cacique | F24: No se dio seguimiento oportuno a una solicitud anterior. | G24: Servicio al Cliente | H24: Media | I24: Resuelto | J24: Sobrecarga de casos en el equipo de servicio al cliente. | K24: Se agendó capacitación para el equipo de servicio al cliente. | L24: 45736 | M24: =IF(L24="","",L24-B24) -> 20 | N24: 0 | O24: Sí
A25: PQRS-024 | B25: 45721 | C25: Queja | D25: Entrega/Logística | E25: Hipermercado Ahorro Costeño | F25: El pedido llegó incompleto; faltaron varias referencias de la orden. | G25: Logística y Distribución | H25: Alta | I25: Abierto | J25: Personal de reparto nuevo sin inducción completa. | M25: =IF(L25="","",L25-B25) | N25: 0 | O25: No
A26: PQRS-025 | B26: 45722 | C26: Reclamo | D26: Entrega/Logística | E26: Clínica San José | F26: Se solicita ampliar la frecuencia de reparto para la zona. | G26: Logística y Distribución | H26: Baja | I26: Cerrado | J26: Error en el alistamiento de pedido en bodega. | K26: Se realizó reposición del producto dañado y se ajustó el embalaje. | L26: 45751 | M26: =IF(L26="","",L26-B26) -> 29 | N26: 0 | O26: Sí
A27: PQRS-026 | B27: 45723 | C27: Reclamo | D27: Entrega/Logística | E27: Hipermercado La Economía | F27: Se recibió mercancía de una referencia distinta a la solicitada. | G27: Logística y Distribución | H27: Media | I27: Resuelto | J27: Error en el alistamiento de pedido en bodega. | K27: Se realizó reposición del producto dañado y se ajustó el embalaje. | L27: 45746 | M27: =IF(L27="","",L27-B27) -> 23 | N27: 0 | O27: Sí
A28: PQRS-027 | B28: 45728 | C28: Queja | D28: Entrega/Logística | E28: Autoservicios Central | F28: Los empaques llegaron golpeados por mal manejo durante el transporte. | G28: Logística y Distribución | H28: Media | I28: En proceso | J28: Congestión vial no prevista en la planeación de ruta. | M28: =IF(L28="","",L28-B28) | N28: 0 | O28: Sí
A29: PQRS-028 | B29: 45738 | C29: Reclamo | D29: Servicio | E29: Tienda El Paisa | F29: El cliente reporta demora en la respuesta del asesor comercial. | G29: Servicio al Cliente | H29: Media | I29: Resuelto | J29: Falta de protocolo claro de respuesta a clientes. | K29: Se reforzó el protocolo de atención con el equipo comercial. | L29: 45740 | M29: =IF(L29="","",L29-B29) -> 2 | N29: 0 | O29: Sí
A30: PQRS-029 | B30: 45740 | C30: Reclamo | D30: Entrega/Logística | E30: Autoservicio San Judas | F30: El pedido llegó incompleto; faltaron varias referencias de la orden. | G30: Logística y Distribución | H30: Media | I30: En proceso | J30: Falla de comunicación entre bodega y transporte. | M30: =IF(L30="","",L30-B30) | N30: 2327000 | O30: Sí
A31: PQRS-030 | B31: 45743 | C31: Queja | D31: Calidad producto | E31: Colegio El Bosque | F31: El cliente reporta presencia de cuerpo extraño en el producto. | G31: Bodega y Almacén | H31: Alta | I31: En proceso | J31: Rotación de inventario (FIFO) no aplicada correctamente en bodega. | M31: =IF(L31="","",L31-B31) | N31: 0 | O31: Sí
A32: PQRS-031 | B32: 45745 | C32: Queja | D32: Entrega/Logística | E32: Interno - Bodega y Almacén | F32: Los empaques llegaron golpeados por mal manejo durante el transporte. | G32: Logística y Distribución | H32: Media | I32: Resuelto | J32: Personal de reparto nuevo sin inducción completa. | K32: Se realizó reposición del producto dañado y se ajustó el embalaje. | L32: 45769 | M32: =IF(L32="","",L32-B32) -> 24 | N32: 0 | O32: Sí
A33: PQRS-032 | B33: 45746 | C33: Queja | D33: Entrega/Logística | E33: Cafetería Empresarial La Popa | F33: El vehículo de reparto llegó fuera del horario pactado con la tienda. | G33: Logística y Distribución | H33: Media | I33: Resuelto | J33: Personal de reparto nuevo sin inducción completa. | K33: Se reasignó la ruta y se coordinó nuevo horario con el cliente. | L33: 45756 | M33: =IF(L33="","",L33-B33) -> 10 | N33: 0 | O33: Sí
A34: PQRS-033 | B34: 45746 | C34: Reclamo | D34: Facturación | E34: Hipermercado La Economía | F34: Existe una diferencia entre el precio pactado y el facturado. | G34: Finanzas y Contabilidad | H34: Media | I34: En proceso | J34: Error de digitación en el sistema de facturación. | M34: =IF(L34="","",L34-B34) | N34: 0 | O34: Sí
A35: PQRS-034 | B35: 45746 | C35: Reclamo | D35: Servicio | E35: Autoservicios La 15 | F35: No se dio seguimiento oportuno a una solicitud anterior. | G35: Servicio al Cliente | H35: Media | I35: Resuelto | J35: Sobrecarga de casos en el equipo de servicio al cliente. | K35: Se reforzó el protocolo de atención con el equipo comercial. | L35: 45757 | M35: =IF(L35="","",L35-B35) -> 11 | N35: 0 | O35: Sí
A36: PQRS-035 | B36: 45747 | C36: Petición | D36: Otra | E36: Hospital Del Caribe | F36: Comentario general sobre la experiencia de compra con la empresa. | G36: Gerencia General | H36: Media | I36: Cerrado | L36: 45772 | M36: =IF(L36="","",L36-B36) -> 25 | N36: 0 | O36: Sí
A37: PQRS-036 | B37: 45748 | C37: Sugerencia | D37: Entrega/Logística | E37: Tienda La 84 | F37: La entrega llegó con más de 3 días de retraso frente a lo acordado. | G37: Logística y Distribución | H37: Baja | I37: Resuelto | L37: 45774 | M37: =IF(L37="","",L37-B37) -> 26 | N37: 0 | O37: Sí
A38: PQRS-037 | B38: 45750 | C38: Reclamo | D38: Entrega/Logística | E38: Interno - Logística y Distribución | F38: Se recibió mercancía de una referencia distinta a la solicitada. | G38: Logística y Distribución | H38: Alta | I38: Cerrado | J38: Personal de reparto nuevo sin inducción completa. | K38: Se reasignó la ruta y se coordinó nuevo horario con el cliente. | L38: 45768 | M38: =IF(L38="","",L38-B38) -> 18 | N38: 867000 | O38: Sí
A39: PQRS-038 | B39: 45752 | C39: Reclamo | D39: Entrega/Logística | E39: Interno - Servicio al Cliente | F39: El pedido llegó incompleto; faltaron varias referencias de la orden. | G39: Logística y Distribución | H39: Alta | I39: En proceso | J39: Ruta de reparto mal planificada para la zona. | M39: =IF(L39="","",L39-B39) | N39: 0 | O39: No
A40: PQRS-039 | B40: 45753 | C40: Reclamo | D40: Calidad producto | E40: Panadería San Fernando | F40: Llegaron unidades con el empaque deteriorado por humedad. | G40: Bodega y Almacén | H40: Media | I40: En proceso | J40: Rotación de inventario (FIFO) no aplicada correctamente en bodega. | M40: =IF(L40="","",L40-B40) | N40: 0 | O40: Sí
A41: PQRS-040 | B41: 45756 | C41: Queja | D41: Entrega/Logística | E41: Autoservicios Ahorro Costeño | F41: La entrega llegó con más de 3 días de retraso frente a lo acordado. | G41: Logística y Distribución | H41: Media | I41: Cerrado | J41: Congestión vial no prevista en la planeación de ruta. | K41: Se reforzó el checklist de alistamiento antes de despacho. | L41: 45780 | M41: =IF(L41="","",L41-B41) -> 24 | N41: 0 | O41: Sí
A42: PQRS-041 | B42: 45762 | C42: Reclamo | D42: Entrega/Logística | E42: Hipermercado Mercar | F42: El pedido llegó incompleto; faltaron varias referencias de la orden. | G42: Logística y Distribución | H42: Media | I42: Resuelto | J42: Falla de comunicación entre bodega y transporte. | K42: Se reasignó la ruta y se coordinó nuevo horario con el cliente. | L42: 45781 | M42: =IF(L42="","",L42-B42) -> 19 | N42: 0 | O42: Sí
A43: PQRS-042 | B43: 45763 | C43: Reclamo | D43: Facturación | E43: Autoservicios Mercar | F43: Se aplicó un descuento por volumen que no correspondía a la compra. | G43: Finanzas y Contabilidad | H43: Alta | I43: En proceso | J43: Descuento aplicado manualmente sin validar la política vigente. | M43: =IF(L43="","",L43-B43) | N43: 0 | O43: Sí
A44: PQRS-043 | B44: 45769 | C44: Queja | D44: Servicio | E44: Super ElGanadero | F44: Se recibió un trato inadecuado por parte del personal de atención. | G44: Servicio al Cliente | H44: Baja | I44: Resuelto | J44: Falta de protocolo claro de respuesta a clientes. | K44: Se agendó capacitación para el equipo de servicio al cliente. | L44: 45777 | M44: =IF(L44="","",L44-B44) -> 8 | N44: 0 | O44: Sí
A45: PQRS-044 | B45: 45769 | C45: Queja | D45: Servicio | E45: Autoservicios El Litoral | F45: El cliente reporta demora en la respuesta del asesor comercial. | G45: Servicio al Cliente | H45: Media | I45: Resuelto | J45: Sobrecarga de casos en el equipo de servicio al cliente. | K45: Se agendó capacitación para el equipo de servicio al cliente. | L45: 45784 | M45: =IF(L45="","",L45-B45) -> 15 | N45: 0 | O45: Sí
A46: PQRS-045 | B46: 45769 | C46: Queja | D46: Calidad producto | E46: Interno - Bodega y Almacén | F46: Llegaron unidades con el empaque deteriorado por humedad. | G46: Bodega y Almacén | H46: Crítica | I46: Resuelto | J46: Defecto de fábrica reportado al proveedor. | K46: Se cambió el producto y se reforzó la rotación FIFO en bodega. | L46: 45774 | M46: =IF(L46="","",L46-B46) -> 5 | N46: 1189000 | O46: No
A47: PQRS-046 | B47: 45773 | C47: Reclamo | D47: Otra | E47: Deposito La Economía | F47: Solicitud de visita comercial para evaluar nuevas líneas de producto. | G47: Gerencia General | H47: Baja | I47: En proceso | J47: Solicitud de información, no aplica causa raíz. | M47: =IF(L47="","",L47-B47) | N47: 0 | O47: No
A48: PQRS-047 | B48: 45773 | C48: Queja | D48: Servicio | E48: Autoservicio La Esquina | F48: No se dio seguimiento oportuno a una solicitud anterior. | G48: Servicio al Cliente | H48: Media | I48: Cerrado | J48: Falta de protocolo claro de respuesta a clientes. | K48: Se reforzó el protocolo de atención con el equipo comercial. | L48: 45787 | M48: =IF(L48="","",L48-B48) -> 14 | N48: 0 | O48: Sí
A49: PQRS-048 | B49: 45775 | C49: Queja | D49: Otra | E49: Minimercado San Judas | F49: Solicitud de información sobre el proceso de vinculación como proveedor. | G49: Gerencia General | H49: Media | I49: Resuelto | J49: Solicitud de información, no aplica causa raíz. | K49: Se brindó la información solicitada al cliente. | L49: 45800 | M49: =IF(L49="","",L49-B49) -> 25 | N49: 0 | O49: Sí
A50: PQRS-049 | B50: 45782 | C50: Reclamo | D50: Calidad producto | E50: Minimercado San Judas | F50: El cliente reporta sabor o textura distinta a la habitual del producto. | G50: Bodega y Almacén | H50: Alta | I50: Resuelto | J50: Rotación de inventario (FIFO) no aplicada correctamente en bodega. | K50: Se ajustaron las condiciones de almacenamiento en la bodega regional. | L50: 45812 | M50: =IF(L50="","",L50-B50) -> 30 | N50: 0 | O50: No
A51: PQRS-050 | B51: 45782 | C51: Reclamo | D51: Entrega/Logística | E51: Supermercado La Canasta | F51: El vehículo de reparto llegó fuera del horario pactado con la tienda. | G51: Logística y Distribución | H51: Media | I51: Resuelto | J51: Ruta de reparto mal planificada para la zona. | K51: Se reasignó la ruta y se coordinó nuevo horario con el cliente. | L51: 45800 | M51: =IF(L51="","",L51-B51) -> 18 | N51: 0 | O51: Sí
A52: PQRS-051 | B52: 45784 | C52: Queja | D52: Calidad producto | E52: Restaurante Nuestra Señora del Carmen | F52: Se encontró un empaque abierto o mal sellado en la caja recibida. | G52: Bodega y Almacén | H52: Baja | I52: Resuelto | J52: Rotación de inventario (FIFO) no aplicada correctamente en bodega. | K52: Se ajustaron las condiciones de almacenamiento en la bodega regional. | L52: 45796 | M52: =IF(L52="","",L52-B52) -> 12 | N52: 0 | O52: Sí
A53: PQRS-052 | B53: 45791 | C53: Reclamo | D53: Entrega/Logística | E53: Hipermercado Ahorro Costeño | F53: El pedido llegó incompleto; faltaron varias referencias de la orden. | G53: Logística y Distribución | H53: Crítica | I53: Resuelto | J53: Falla de comunicación entre bodega y transporte. | K53: Se realizó reposición del producto dañado y se ajustó el embalaje. | L53: 45819 | M53: =IF(L53="","",L53-B53) -> 28 | N53: 2347000 | O53: Sí
A54: PQRS-053 | B54: 45791 | C54: Queja | D54: Servicio | E54: Cafetería Empresarial San Fernando | F54: Se recibió un trato inadecuado por parte del personal de atención. | G54: Servicio al Cliente | H54: Alta | I54: Cerrado | J54: Sobrecarga de casos en el equipo de servicio al cliente. | K54: Se realizó llamada de disculpas y seguimiento personalizado. | L54: 45806 | M54: =IF(L54="","",L54-B54) -> 15 | N54: 0 | O54: Sí
A55: PQRS-054 | B55: 45793 | C55: Petición | D55: Entrega/Logística | E55: Restaurante Nuestra Señora del Carmen | F55: La entrega llegó con más de 3 días de retraso frente a lo acordado. | G55: Logística y Distribución | H55: Media | I55: Resuelto | L55: 45817 | M55: =IF(L55="","",L55-B55) -> 24 | N55: 0 | O55: Sí
A56: PQRS-055 | B56: 45799 | C56: Reclamo | D56: Servicio | E56: Autoservicio El Faro | F56: El cliente solicita más información sobre el catálogo de productos. | G56: Servicio al Cliente | H56: Alta | I56: Resuelto | J56: Sobrecarga de casos en el equipo de servicio al cliente. | K56: Se realizó llamada de disculpas y seguimiento personalizado. | L56: 45814 | M56: =IF(L56="","",L56-B56) -> 15 | N56: 0 | O56: Sí
A57: PQRS-056 | B57: 45800 | C57: Sugerencia | D57: Calidad producto | E57: Fundación Nuestra Señora del Carmen | F57: Se encontró un empaque abierto o mal sellado en la caja recibida. | G57: Bodega y Almacén | H57: Media | I57: Cerrado | L57: 45806 | M57: =IF(L57="","",L57-B57) -> 6 | N57: 0 | O57: Sí
A58: PQRS-057 | B58: 45801 | C58: Queja | D58: Facturación | E58: Autoservicio La Costeña | F58: El cliente solicita una copia de la factura para su contabilidad. | G58: Finanzas y Contabilidad | H58: Media | I58: Resuelto | J58: Descuento aplicado manualmente sin validar la política vigente. | K58: Se generó nota crédito y se corrigió la factura. | L58: 45810 | M58: =IF(L58="","",L58-B58) -> 9 | N58: 0 | O58: Sí
A59: PQRS-058 | B59: 45804 | C59: Queja | D59: Facturación | E59: Hipermercado La Canasta | F59: La factura tiene un valor distinto al acordado en el pedido. | G59: Finanzas y Contabilidad | H59: Media | I59: Resuelto | J59: Falla en el envío automático de la factura electrónica. | K59: Se reenvió la factura electrónica al correo del cliente. | L59: 45810 | M59: =IF(L59="","",L59-B59) -> 6 | N59: 0 | O59: No
A60: PQRS-059 | B60: 45805 | C60: Reclamo | D60: Facturación | E60: Colegio El Bosque | F60: Se cobró un producto que no fue entregado. | G60: Finanzas y Contabilidad | H60: Alta | I60: Resuelto | J60: Descuento aplicado manualmente sin validar la política vigente. | K60: Se generó nota crédito y se corrigió la factura. | L60: 45830 | M60: =IF(L60="","",L60-B60) -> 25 | N60: 0 | O60: Sí
A61: PQRS-060 | B61: 45807 | C61: Reclamo | D61: Calidad producto | E61: Fundación La Sagrada Familia | F61: El producto llegó próximo a su fecha de vencimiento. | G61: Bodega y Almacén | H61: Alta | I61: Resuelto | J61: Defecto de fábrica reportado al proveedor. | K61: Se retiró el lote afectado y se notificó al proveedor. | L61: 45819 | M61: =IF(L61="","",L61-B61) -> 12 | N61: 1645000 | O61: No
A62: PQRS-061 | B62: 45807 | C62: Petición | D62: Entrega/Logística | E62: Autoservicio El Trebol | F62: La entrega llegó con más de 3 días de retraso frente a lo acordado. | G62: Logística y Distribución | H62: Alta | I62: Cerrado | L62: 45810 | M62: =IF(L62="","",L62-B62) -> 3 | N62: 0 | O62: Sí
A63: PQRS-062 | B63: 45811 | C63: Sugerencia | D63: Entrega/Logística | E63: Colegio El Bosque | F63: El conductor no llamó antes de la entrega, generando reprogramación. | G63: Logística y Distribución | H63: Media | I63: Resuelto | L63: 45826 | M63: =IF(L63="","",L63-B63) -> 15 | N63: 0 | O63: Sí
A64: PQRS-063 | B64: 45811 | C64: Petición | D64: Entrega/Logística | E64: Interno - Servicio al Cliente | F64: El conductor no llamó antes de la entrega, generando reprogramación. | G64: Logística y Distribución | H64: Baja | I64: Cerrado | L64: 45827 | M64: =IF(L64="","",L64-B64) -> 16 | N64: 0 | O64: Sí
A65: PQRS-064 | B65: 45811 | C65: Queja | D65: Calidad producto | E65: Supermercado Todo Fresco | F65: Se solicita revisar la calidad del último lote despachado. | G65: Bodega y Almacén | H65: Baja | I65: Resuelto | J65: Condiciones de almacenamiento inadecuadas (humedad/temperatura). | K65: Se cambió el producto y se reforzó la rotación FIFO en bodega. | L65: 45814 | M65: =IF(L65="","",L65-B65) -> 3 | N65: 318000 | O65: Sí
A66: PQRS-065 | B66: 45811 | C66: Reclamo | D66: Entrega/Logística | E66: Hipermercado La Canasta | F66: Se solicita ampliar la frecuencia de reparto para la zona. | G66: Logística y Distribución | H66: Media | I66: Resuelto | J66: Personal de reparto nuevo sin inducción completa. | K66: Se reenvió el faltante en un despacho adicional sin costo. | L66: 45835 | M66: =IF(L66="","",L66-B66) -> 24 | N66: 0 | O66: Sí
A67: PQRS-066 | B67: 45817 | C67: Reclamo | D67: Entrega/Logística | E67: Interno - Logística y Distribución | F67: Se solicita ampliar la frecuencia de reparto para la zona. | G67: Logística y Distribución | H67: Media | I67: Cerrado | J67: Falla de comunicación entre bodega y transporte. | K67: Se reasignó la ruta y se coordinó nuevo horario con el cliente. | L67: 45841 | M67: =IF(L67="","",L67-B67) -> 24 | N67: 0 | O67: Sí
A68: PQRS-067 | B68: 45820 | C68: Queja | D68: Calidad producto | E68: Interno - Bodega y Almacén | F68: Llegaron unidades con el empaque deteriorado por humedad. | G68: Bodega y Almacén | H68: Baja | I68: Resuelto | J68: Defecto de fábrica reportado al proveedor. | K68: Se retiró el lote afectado y se notificó al proveedor. | L68: 45835 | M68: =IF(L68="","",L68-B68) -> 15 | N68: 0 | O68: Sí
A69: PQRS-068 | B69: 45823 | C69: Sugerencia | D69: Entrega/Logística | E69: Minimercado Don Pedro | F69: El vehículo de reparto llegó fuera del horario pactado con la tienda. | G69: Logística y Distribución | H69: Media | I69: Resuelto | L69: 45851 | M69: =IF(L69="","",L69-B69) -> 28 | N69: 0 | O69: Sí
A70: PQRS-069 | B70: 45825 | C70: Petición | D70: Entrega/Logística | E70: Super La 15 | F70: El vehículo de reparto llegó fuera del horario pactado con la tienda. | G70: Logística y Distribución | H70: Baja | I70: Resuelto | L70: 45834 | M70: =IF(L70="","",L70-B70) -> 9 | N70: 0 | O70: Sí
A71: PQRS-070 | B71: 45828 | C71: Queja | D71: Entrega/Logística | E71: Autoservicio Santa Rita | F71: El pedido llegó incompleto; faltaron varias referencias de la orden. | G71: Logística y Distribución | H71: Crítica | I71: Resuelto | J71: Personal de reparto nuevo sin inducción completa. | K71: Se reenvió el faltante en un despacho adicional sin costo. | L71: 45840 | M71: =IF(L71="","",L71-B71) -> 12 | N71: 0 | O71: No
A72: PQRS-071 | B72: 45828 | C72: Petición | D72: Facturación | E72: Autoservicio Doña María | F72: El cliente solicita una copia de la factura para su contabilidad. | G72: Finanzas y Contabilidad | H72: Media | I72: Resuelto | L72: 45833 | M72: =IF(L72="","",L72-B72) -> 5 | N72: 0 | O72: No
A73: PQRS-072 | B73: 45830 | C73: Reclamo | D73: Entrega/Logística | E73: Autoservicios Mercar | F73: La factura no coincidió con las cantidades físicas entregadas. | G73: Logística y Distribución | H73: Media | I73: Resuelto | J73: Ruta de reparto mal planificada para la zona. | K73: Se realizó reposición del producto dañado y se ajustó el embalaje. | L73: 45835 | M73: =IF(L73="","",L73-B73) -> 5 | N73: 831000 | O73: Sí
A74: PQRS-073 | B74: 45835 | C74: Sugerencia | D74: Facturación | E74: Hipermercado Mercar | F74: El cliente no ha recibido la factura electrónica del pedido. | G74: Finanzas y Contabilidad | H74: Baja | I74: Resuelto | L74: 45838 | M74: =IF(L74="","",L74-B74) -> 3 | N74: 0 | O74: Sí
A75: PQRS-074 | B75: 45840 | C75: Reclamo | D75: Entrega/Logística | E75: Autoservicios La Economía | F75: Se solicita ampliar la frecuencia de reparto para la zona. | G75: Logística y Distribución | H75: Media | I75: Cerrado | J75: Falla de comunicación entre bodega y transporte. | K75: Se reenvió el faltante en un despacho adicional sin costo. | L75: 45847 | M75: =IF(L75="","",L75-B75) -> 7 | N75: 595000 | O75: Sí
A76: PQRS-075 | B76: 45843 | C76: Queja | D76: Entrega/Logística | E76: Cafetería Empresarial San Fernando | F76: El conductor no llamó antes de la entrega, generando reprogramación. | G76: Logística y Distribución | H76: Media | I76: En proceso | J76: Falla de comunicación entre bodega y transporte. | M76: =IF(L76="","",L76-B76) | N76: 0 | O76: Sí
A77: PQRS-076 | B77: 45845 | C77: Reclamo | D77: Calidad producto | E77: Hipermercado La Riviera | F77: Se encontró un empaque abierto o mal sellado en la caja recibida. | G77: Bodega y Almacén | H77: Media | I77: Resuelto | J77: Defecto de fábrica reportado al proveedor. | K77: Se retiró el lote afectado y se notificó al proveedor. | L77: 45871 | M77: =IF(L77="","",L77-B77) -> 26 | N77: 995000 | O77: Sí
A78: PQRS-077 | B78: 45852 | C78: Petición | D78: Calidad producto | E78: Interno - Bodega y Almacén | F78: El cliente reporta sabor o textura distinta a la habitual del producto. | G78: Bodega y Almacén | H78: Crítica | I78: Cerrado | L78: 45858 | M78: =IF(L78="","",L78-B78) -> 6 | N78: 0 | O78: Sí
A79: PQRS-078 | B79: 45854 | C79: Reclamo | D79: Servicio | E79: Panadería Del Caribe | F79: No se dio seguimiento oportuno a una solicitud anterior. | G79: Servicio al Cliente | H79: Alta | I79: Cerrado | J79: Capacitación insuficiente del personal de atención. | K79: Se realizó llamada de disculpas y seguimiento personalizado. | L79: 45856 | M79: =IF(L79="","",L79-B79) -> 2 | N79: 0 | O79: Sí
A80: PQRS-079 | B80: 45856 | C80: Queja | D80: Servicio | E80: Supermercado ElGanadero | F80: El cliente sugiere mejorar los canales de comunicación con la empresa. | G80: Servicio al Cliente | H80: Media | I80: Resuelto | J80: Falta de protocolo claro de respuesta a clientes. | K80: Se agendó capacitación para el equipo de servicio al cliente. | L80: 45886 | M80: =IF(L80="","",L80-B80) -> 30 | N80: 0 | O80: Sí
A81: PQRS-080 | B81: 45859 | C81: Petición | D81: Entrega/Logística | E81: Hipermercado Ahorro Costeño | F81: Se recibió mercancía de una referencia distinta a la solicitada. | G81: Logística y Distribución | H81: Alta | I81: Resuelto | L81: 45862 | M81: =IF(L81="","",L81-B81) -> 3 | N81: 0 | O81: Sí
A82: PQRS-081 | B82: 45861 | C82: Reclamo | D82: Entrega/Logística | E82: Autoservicios La 15 | F82: Se solicita ampliar la frecuencia de reparto para la zona. | G82: Logística y Distribución | H82: Alta | I82: Cerrado | J82: Personal de reparto nuevo sin inducción completa. | K82: Se reforzó el checklist de alistamiento antes de despacho. | L82: 45881 | M82: =IF(L82="","",L82-B82) -> 20 | N82: 377000 | O82: Sí
A83: PQRS-082 | B83: 45861 | C83: Reclamo | D83: Facturación | E83: Autoservicio El Trebol | F83: El cliente no ha recibido la factura electrónica del pedido. | G83: Finanzas y Contabilidad | H83: Media | I83: Resuelto | J83: Error de digitación en el sistema de facturación. | K83: Se ajustó el descuento aplicado según política vigente. | L83: 45888 | M83: =IF(L83="","",L83-B83) -> 27 | N83: 0 | O83: Sí
A84: PQRS-083 | B84: 45862 | C84: Reclamo | D84: Calidad producto | E84: Supermercado Ahorro Costeño | F84: Llegaron unidades con el empaque deteriorado por humedad. | G84: Bodega y Almacén | H84: Alta | I84: Cerrado | J84: Defecto de fábrica reportado al proveedor. | K84: Se cambió el producto y se reforzó la rotación FIFO en bodega. | L84: 45874 | M84: =IF(L84="","",L84-B84) -> 12 | N84: 0 | O84: Sí
A85: PQRS-084 | B85: 45863 | C85: Reclamo | D85: Entrega/Logística | E85: Minimercado La Esquina | F85: El vehículo de reparto llegó fuera del horario pactado con la tienda. | G85: Logística y Distribución | H85: Alta | I85: Resuelto | J85: Falla de comunicación entre bodega y transporte. | K85: Se reforzó el checklist de alistamiento antes de despacho. | L85: 45882 | M85: =IF(L85="","",L85-B85) -> 19 | N85: 0 | O85: Sí
A86: PQRS-085 | B86: 45865 | C86: Queja | D86: Entrega/Logística | E86: Deposito La Economía | F86: Se recibió mercancía de una referencia distinta a la solicitada. | G86: Logística y Distribución | H86: Media | I86: Resuelto | J86: Personal de reparto nuevo sin inducción completa. | K86: Se reforzó el checklist de alistamiento antes de despacho. | L86: 45884 | M86: =IF(L86="","",L86-B86) -> 19 | N86: 0 | O86: Sí
A87: PQRS-086 | B87: 45869 | C87: Queja | D87: Entrega/Logística | E87: Autoservicios El Litoral | F87: La factura no coincidió con las cantidades físicas entregadas. | G87: Logística y Distribución | H87: Crítica | I87: Resuelto | J87: Error en el alistamiento de pedido en bodega. | K87: Se reasignó la ruta y se coordinó nuevo horario con el cliente. | L87: 45895 | M87: =IF(L87="","",L87-B87) -> 26 | N87: 0 | O87: Sí
A88: PQRS-087 | B88: 45871 | C88: Reclamo | D88: Servicio | E88: Tienda Nueva Vida | F88: No se dio seguimiento oportuno a una solicitud anterior. | G88: Servicio al Cliente | H88: Media | I88: Resuelto | J88: Falta de protocolo claro de respuesta a clientes. | K88: Se realizó llamada de disculpas y seguimiento personalizado. | L88: 45894 | M88: =IF(L88="","",L88-B88) -> 23 | N88: 0 | O88: Sí
A89: PQRS-088 | B89: 45872 | C89: Reclamo | D89: Servicio | E89: Deposito El Faro | F89: No se dio seguimiento oportuno a una solicitud anterior. | G89: Servicio al Cliente | H89: Alta | I89: Resuelto | J89: Capacitación insuficiente del personal de atención. | K89: Se realizó llamada de disculpas y seguimiento personalizado. | L89: 45887 | M89: =IF(L89="","",L89-B89) -> 15 | N89: 0 | O89: Sí
A90: PQRS-089 | B90: 45874 | C90: Reclamo | D90: Calidad producto | E90: Super Mercar | F90: Se identificó un lote con etiquetado incorrecto de fecha de vencimiento. | G90: Bodega y Almacén | H90: Media | I90: Cerrado | J90: Defecto de fábrica reportado al proveedor. | K90: Se cambió el producto y se reforzó la rotación FIFO en bodega. | L90: 45882 | M90: =IF(L90="","",L90-B90) -> 8 | N90: 0 | O90: Sí
A91: PQRS-090 | B91: 45878 | C91: Reclamo | D91: Calidad producto | E91: Super El Cacique | F91: El cliente reporta presencia de cuerpo extraño en el producto. | G91: Bodega y Almacén | H91: Alta | I91: Resuelto | J91: Defecto de fábrica reportado al proveedor. | K91: Se cambió el producto y se reforzó la rotación FIFO en bodega. | L91: 45883 | M91: =IF(L91="","",L91-B91) -> 5 | N91: 0 | O91: Sí
A92: PQRS-091 | B92: 45882 | C92: Queja | D92: Facturación | E92: Autoservicios El Baratillo | F92: El cliente no ha recibido la factura electrónica del pedido. | G92: Finanzas y Contabilidad | H92: Media | I92: Resuelto | J92: Error de digitación en el sistema de facturación. | K92: Se ajustó el descuento aplicado según política vigente. | L92: 45896 | M92: =IF(L92="","",L92-B92) -> 14 | N92: 0 | O92: Sí
A93: PQRS-092 | B93: 45882 | C93: Queja | D93: Entrega/Logística | E93: Hotel La Bahía | F93: Se recibió mercancía de una referencia distinta a la solicitada. | G93: Logística y Distribución | H93: Crítica | I93: Resuelto | J93: Personal de reparto nuevo sin inducción completa. | K93: Se reasignó la ruta y se coordinó nuevo horario con el cliente. | L93: 45900 | M93: =IF(L93="","",L93-B93) -> 18 | N93: 293000 | O93: Sí
A94: PQRS-093 | B94: 45884 | C94: Queja | D94: Facturación | E94: Supermercado El Rey | F94: Se cobró un producto que no fue entregado. | G94: Finanzas y Contabilidad | H94: Media | I94: En proceso | J94: Falla en el envío automático de la factura electrónica. | M94: =IF(L94="","",L94-B94) | N94: 0 | O94: Sí
A95: PQRS-094 | B95: 45885 | C95: Reclamo | D95: Entrega/Logística | E95: Hospital El Bosque | F95: Se recibió mercancía de una referencia distinta a la solicitada. | G95: Logística y Distribución | H95: Baja | I95: Resuelto | J95: Error en el alistamiento de pedido en bodega. | K95: Se reenvió el faltante en un despacho adicional sin costo. | L95: 45900 | M95: =IF(L95="","",L95-B95) -> 15 | N95: 0 | O95: Sí
A96: PQRS-095 | B96: 45889 | C96: Queja | D96: Servicio | E96: Autoservicio La Costeña | F96: El cliente reporta demora en la respuesta del asesor comercial. | G96: Servicio al Cliente | H96: Media | I96: Cerrado | J96: Capacitación insuficiente del personal de atención. | K96: Se reforzó el protocolo de atención con el equipo comercial. | L96: 45900 | M96: =IF(L96="","",L96-B96) -> 11 | N96: 0 | O96: Sí
A97: PQRS-096 | B97: 45892 | C97: Petición | D97: Entrega/Logística | E97: Interno - Servicio al Cliente | F97: Se solicita ampliar la frecuencia de reparto para la zona. | G97: Logística y Distribución | H97: Media | I97: Cerrado | L97: 45900 | M97: =IF(L97="","",L97-B97) -> 8 | N97: 0 | O97: Sí
A98: PQRS-097 | B98: 45894 | C98: Queja | D98: Entrega/Logística | E98: Fundación La Sagrada Familia | F98: Se solicita ampliar la frecuencia de reparto para la zona. | G98: Logística y Distribución | H98: Baja | I98: Resuelto | J98: Falla de comunicación entre bodega y transporte. | K98: Se reasignó la ruta y se coordinó nuevo horario con el cliente. | L98: 45900 | M98: =IF(L98="","",L98-B98) -> 6 | N98: 1323000 | O98: Sí
A99: PQRS-098 | B99: 45895 | C99: Queja | D99: Entrega/Logística | E99: Deposito Don Pedro | F99: El vehículo de reparto llegó fuera del horario pactado con la tienda. | G99: Logística y Distribución | H99: Media | I99: Resuelto | J99: Error en el alistamiento de pedido en bodega. | K99: Se realizó reposición del producto dañado y se ajustó el embalaje. | L99: 45900 | M99: =IF(L99="","",L99-B99) -> 5 | N99: 490000 | O99: Sí
A100: PQRS-099 | B100: 45899 | C100: Reclamo | D100: Entrega/Logística | E100: Minimercado Don Pedro | F100: Los empaques llegaron golpeados por mal manejo durante el transporte. | G100: Logística y Distribución | H100: Media | I100: Resuelto | J100: Ruta de reparto mal planificada para la zona. | K100: Se reforzó el checklist de alistamiento antes de despacho. | L100: 45900 | M100: =IF(L100="","",L100-B100) -> 1 | N100: 0 | O100: Sí
...

Sheet Resumen
A1: Resumen — PQRS y Control de Calidad 2025 (Andina Foods S.A.S.)
A3: Total de casos registrados | B3: =COUNTA(Detalle!A2:A101) -> 100
A5: Peticiones | B5: =COUNTIF(Detalle!C2:C101,"Petición") -> 15
A6: Quejas | B6: =COUNTIF(Detalle!C2:C101,"Queja") -> 34
A7: Reclamos | B7: =COUNTIF(Detalle!C2:C101,"Reclamo") -> 41
A8: Sugerencias | B8: =COUNTIF(Detalle!C2:C101,"Sugerencia") -> 10
A10: Abiertos | B10: =COUNTIF(Detalle!I2:I101,"Abierto") -> 2
A11: En proceso | B11: =COUNTIF(Detalle!I2:I101,"En proceso") -> 15
A12: Resueltos | B12: =COUNTIF(Detalle!I2:I101,"Resuelto") -> 63
A13: Cerrados | B13: =COUNTIF(Detalle!I2:I101,"Cerrado") -> 20
A14: % Resuelto + Cerrado | B14: =(B12+B13)/B3 -> 0.83
A15: % Abierto + En proceso | B15: =(B10+B11)/B3 -> 0.17
A17: Costo total de impacto (COP) | B17: =SUM(Detalle!N2:N101) -> 24385000
A18: Días promedio de resolución (casos resueltos) | B18: =AVERAGEIF(Detalle!I2:I101,"Resuelto",Detalle!M2:M101) -> 15.539683
A20: Casos sin seguimiento y aún abiertos/en proceso (alerta) | B20: =SUMPRODUCT((Detalle!I2:I101<>"Resuelto")*(Detalle!I2:I101<>"Cerrado")*(Detalle!O2:O101="No")) -> 3
A22: Promedio de Días de Resolución por Categoría
A23: Categoría | B23: # Casos | C23: # Resueltos/Cerrados | D23: Días Promedio Resolución | E23: Costo Impacto (COP)
A24: Entrega/Logística | B24: =COUNTIF(Detalle!D2:D101,"Entrega/Logística") -> 48 | C24: =COUNTIFS(Detalle!D2:D101,"Entrega/Logística",Detalle!I2:I101,"Resuelto")+COUNTIFS(Detalle!D2:D101,"Entrega/Logística",Detalle!I2:I101,"Cerrado") -> 39 | D24: =IFERROR((SUMIFS(Detalle!M2:M101,Detalle!D2:D101,"Entrega/Logística",Detalle!I2:I101,"Resuelto")+SUMIFS(Detalle!M2:M101,Detalle!D2:D101,"Entrega/Logística",Detalle!I2:I101,"Cerrado"))/C24,0) -> 17.461538 | E24: =SUMIF(Detalle!D2:D101,"Entrega/Logística",Detalle!N2:N101) -> 18532000
A25: Calidad producto | B25: =COUNTIF(Detalle!D2:D101,"Calidad producto") -> 19 | C25: =COUNTIFS(Detalle!D2:D101,"Calidad producto",Detalle!I2:I101,"Resuelto")+COUNTIFS(Detalle!D2:D101,"Calidad producto",Detalle!I2:I101,"Cerrado") -> 17 | D25: =IFERROR((SUMIFS(Detalle!M2:M101,Detalle!D2:D101,"Calidad producto",Detalle!I2:I101,"Resuelto")+SUMIFS(Detalle!M2:M101,Detalle!D2:D101,"Calidad producto",Detalle!I2:I101,"Cerrado"))/C25,0) -> 12.117647 | E25: =SUMIF(Detalle!D2:D101,"Calidad producto",Detalle!N2:N101) -> 5853000
A26: Facturación | B26: =COUNTIF(Detalle!D2:D101,"Facturación") -> 14 | C26: =COUNTIFS(Detalle!D2:D101,"Facturación",Detalle!I2:I101,"Resuelto")+COUNTIFS(Detalle!D2:D101,"Facturación",Detalle!I2:I101,"Cerrado") -> 9 | D26: =IFERROR((SUMIFS(Detalle!M2:M101,Detalle!D2:D101,"Facturación",Detalle!I2:I101,"Resuelto")+SUMIFS(Detalle!M2:M101,Detalle!D2:D101,"Facturación",Detalle!I2:I101,"Cerrado"))/C26,0) -> 10.333333 | E26: =SUMIF(Detalle!D2:D101,"Facturación",Detalle!N2:N101) -> 0
A27: Servicio | B27: =COUNTIF(Detalle!D2:D101,"Servicio") -> 14 | C27: =COUNTIFS(Detalle!D2:D101,"Servicio",Detalle!I2:I101,"Resuelto")+COUNTIFS(Detalle!D2:D101,"Servicio",Detalle!I2:I101,"Cerrado") -> 14 | D27: =IFERROR((SUMIFS(Detalle!M2:M101,Detalle!D2:D101,"Servicio",Detalle!I2:I101,"Resuelto")+SUMIFS(Detalle!M2:M101,Detalle!D2:D101,"Servicio",Detalle!I2:I101,"Cerrado"))/C27,0) -> 14.785714 | E27: =SUMIF(Detalle!D2:D101,"Servicio",Detalle!N2:N101) -> 0
A28: Otra | B28: =COUNTIF(Detalle!D2:D101,"Otra") -> 5 | C28: =COUNTIFS(Detalle!D2:D101,"Otra",Detalle!I2:I101,"Resuelto")+COUNTIFS(Detalle!D2:D101,"Otra",Detalle!I2:I101,"Cerrado") -> 4 | D28: =IFERROR((SUMIFS(Detalle!M2:M101,Detalle!D2:D101,"Otra",Detalle!I2:I101,"Resuelto")+SUMIFS(Detalle!M2:M101,Detalle!D2:D101,"Otra",Detalle!I2:I101,"Cerrado"))/C28,0) -> 18.75 | E28: =SUMIF(Detalle!D2:D101,"Otra",Detalle!N2:N101) -> 0
A30: Tendencia Mensual de Casos (Enero-Agosto 2025)
A31: Mes | B31: # Casos Registrados | C31: # Reclamos | D31: # Quejas | E31: Costo Impacto (COP)
A32: Enero | B32: =SUMPRODUCT((TEXT(Detalle!B2:B101,"YYYY-MM")="2025-01")*1) -> 11 | C32: =SUMPRODUCT((TEXT(Detalle!B2:B101,"YYYY-MM")="2025-01")*(Detalle!C2:C101="Reclamo")) -> 4 | D32: =SUMPRODUCT((TEXT(Detalle!B2:B101,"YYYY-MM")="2025-01")*(Detalle!C2:C101="Queja")) -> 1 | E32: =SUMPRODUCT((TEXT(Detalle!B2:B101,"YYYY-MM")="2025-01")*Detalle!N2:N101) -> 3842000
A33: Febrero | B33: =SUMPRODUCT((TEXT(Detalle!B2:B101,"YYYY-MM")="2025-02")*1) -> 12 | C33: =SUMPRODUCT((TEXT(Detalle!B2:B101,"YYYY-MM")="2025-02")*(Detalle!C2:C101="Reclamo")) -> 3 | D33: =SUMPRODUCT((TEXT(Detalle!B2:B101,"YYYY-MM")="2025-02")*(Detalle!C2:C101="Queja")) -> 5 | E33: =SUMPRODUCT((TEXT(Detalle!B2:B101,"YYYY-MM")="2025-02")*Detalle!N2:N101) -> 6946000
A34: Marzo | B34: =SUMPRODUCT((TEXT(Detalle!B2:B101,"YYYY-MM")="2025-03")*1) -> 12 | C34: =SUMPRODUCT((TEXT(Detalle!B2:B101,"YYYY-MM")="2025-03")*(Detalle!C2:C101="Reclamo")) -> 6 | D34: =SUMPRODUCT((TEXT(Detalle!B2:B101,"YYYY-MM")="2025-03")*(Detalle!C2:C101="Queja")) -> 5 | E34: =SUMPRODUCT((TEXT(Detalle!B2:B101,"YYYY-MM")="2025-03")*Detalle!N2:N101) -> 2327000
A35: Abril | B35: =SUMPRODUCT((TEXT(Detalle!B2:B101,"YYYY-MM")="2025-04")*1) -> 13 | C35: =SUMPRODUCT((TEXT(Detalle!B2:B101,"YYYY-MM")="2025-04")*(Detalle!C2:C101="Reclamo")) -> 6 | D35: =SUMPRODUCT((TEXT(Detalle!B2:B101,"YYYY-MM")="2025-04")*(Detalle!C2:C101="Queja")) -> 6 | E35: =SUMPRODUCT((TEXT(Detalle!B2:B101,"YYYY-MM")="2025-04")*Detalle!N2:N101) -> 2056000
A36: Mayo | B36: =SUMPRODUCT((TEXT(Detalle!B2:B101,"YYYY-MM")="2025-05")*1) -> 13 | C36: =SUMPRODUCT((TEXT(Detalle!B2:B101,"YYYY-MM")="2025-05")*(Detalle!C2:C101="Reclamo")) -> 6 | D36: =SUMPRODUCT((TEXT(Detalle!B2:B101,"YYYY-MM")="2025-05")*(Detalle!C2:C101="Queja")) -> 4 | E36: =SUMPRODUCT((TEXT(Detalle!B2:B101,"YYYY-MM")="2025-05")*Detalle!N2:N101) -> 3992000
A37: Junio | B37: =SUMPRODUCT((TEXT(Detalle!B2:B101,"YYYY-MM")="2025-06")*1) -> 12 | C37: =SUMPRODUCT((TEXT(Detalle!B2:B101,"YYYY-MM")="2025-06")*(Detalle!C2:C101="Reclamo")) -> 3 | D37: =SUMPRODUCT((TEXT(Detalle!B2:B101,"YYYY-MM")="2025-06")*(Detalle!C2:C101="Queja")) -> 3 | E37: =SUMPRODUCT((TEXT(Detalle!B2:B101,"YYYY-MM")="2025-06")*Detalle!N2:N101) -> 1149000
A38: Julio | B38: =SUMPRODUCT((TEXT(Detalle!B2:B101,"YYYY-MM")="2025-07")*1) -> 13 | C38: =SUMPRODUCT((TEXT(Detalle!B2:B101,"YYYY-MM")="2025-07")*(Detalle!C2:C101="Reclamo")) -> 7 | D38: =SUMPRODUCT((TEXT(Detalle!B2:B101,"YYYY-MM")="2025-07")*(Detalle!C2:C101="Queja")) -> 4 | E38: =SUMPRODUCT((TEXT(Detalle!B2:B101,"YYYY-MM")="2025-07")*Detalle!N2:N101) -> 1967000
A39: Agosto | B39: =SUMPRODUCT((TEXT(Detalle!B2:B101,"YYYY-MM")="2025-08")*1) -> 14 | C39: =SUMPRODUCT((TEXT(Detalle!B2:B101,"YYYY-MM")="2025-08")*(Detalle!C2:C101="Reclamo")) -> 6 | D39: =SUMPRODUCT((TEXT(Detalle!B2:B101,"YYYY-MM")="2025-08")*(Detalle!C2:C101="Queja")) -> 6 | E39: =SUMPRODUCT((TEXT(Detalle!B2:B101,"YYYY-MM")="2025-08")*Detalle!N2:N101) -> 2106000
A42: Nota: datos simulados con fines de demostración / analítica del programa Master IA Local. No corresponden a PQRS reales de Andina Foods S.A.S.
