Workbook

Sheet Transacciones
A1: Fecha | B1: Documento | C1: ID Cliente | D1: Cliente | E1: SKU Producto | F1: Producto | G1: Categoría | H1: Canal | I1: Cantidad | J1: Valor Unitario (COP) | K1: Valor Total (COP) | L1: Descuento % | M1: Valor Neto (COP) | N1: % Costo COGS | O1: Costo COGS (COP) | P1: Utilidad Bruta (COP) | Q1: Estado | R1: Mes
A2: 45658 | B2: FAC001 | C2: C087 | D2: Minimercado La Fe | E2: P110 | F2: Atún en Lata Lata 170g (99) | G2: Alimentos | H2: Tienda tradicional | I2: 808 | J2: 14670 | K2: =I2*J2 -> 11853360 | L2: 0.093 | M2: =K2*(1-L2) -> 10750998 | N2: 0.747 | O2: =M2*N2 -> 8030995.1 | P2: =M2-O2 -> 2720002.4 | Q2: Pagado | R2: =TEXT(A2,"YYYY-MM") -> 2025-01
A3: 45658 | B3: FAC002 | C3: C142 | D3: Minimercado San Judas | E3: P082 | F3: Café Instantáneo Frasco 170g (76) | G3: Bebidas | H3: Tienda tradicional | I3: 629 | J3: 8000 | K3: =I3*J3 -> 5032000 | L3: 0.147 | M3: =K3*(1-L3) -> 4292296 | N3: 0.634 | O3: =M3*N3 -> 2721315.7 | P3: =M3-O3 -> 1570980.3 | Q3: Pagado | R3: =TEXT(A3,"YYYY-MM") -> 2025-01
A4: 45659 | B4: FAC003 | C4: C032 | D4: Clínica El Marqués | E4: P015 | F4: Jugo de Naranja Natural 1L | G4: Marca propia | H4: Institucional | I4: 237 | J4: 7860 | K4: =I4*J4 -> 1862820 | L4: 0 | M4: =K4*(1-L4) -> 1862820 | N4: 0.623 | O4: =M4*N4 -> 1160536.9 | P4: =M4-O4 -> 702283.14 | Q4: Pagado | R4: =TEXT(A4,"YYYY-MM") -> 2025-01
A5: 45660 | B5: FAC004 | C5: C059 | D5: Supermercado El Rey | E5: P013 | F5: Atún en Lata Lata 170g | G5: Alimentos | H5: Supermercado | I5: 236 | J5: 9950 | K5: =I5*J5 -> 2348200 | L5: 0 | M5: =K5*(1-L5) -> 2348200 | N5: 0.607 | O5: =M5*N5 -> 1425357.4 | P5: =M5-O5 -> 922842.6 | Q5: Pagado | R5: =TEXT(A5,"YYYY-MM") -> 2025-01
A6: 45662 | B6: FAC005 | C6: C075 | D6: Autoservicios La Economía | E6: P039 | F6: Gaseosa Sabor Cola 1.5L | G6: Bebidas | H6: Supermercado | I6: 272 | J6: 7530 | K6: =I6*J6 -> 2048160 | L6: 0.001 | M6: =K6*(1-L6) -> 2046111.8 | N6: 0.661 | O6: =M6*N6 -> 1352479.9 | P6: =M6-O6 -> 693631.91 | Q6: Pagado | R6: =TEXT(A6,"YYYY-MM") -> 2025-01
A7: 45662 | B7: FAC006 | C7: C050 | D7: Autoservicios La Bonanza | E7: P073 | F7: Avena Lista para Tomar 1L (32) | G7: Bebidas | H7: Supermercado | I7: 655 | J7: 6980 | K7: =I7*J7 -> 4571900 | L7: 0.123 | M7: =K7*(1-L7) -> 4009556.3 | N7: 0.618 | O7: =M7*N7 -> 2477905.8 | P7: =M7-O7 -> 1531650.5 | Q7: Pagado | R7: =TEXT(A7,"YYYY-MM") -> 2025-01
A8: 45662 | B8: FAC007 | C8: C084 | D8: Hospital Santa Marta de la Sierra | E8: P036 | F8: Ponqué Industrial Paquete 220g | G8: Alimentos | H8: Institucional | I8: 372 | J8: 9910 | K8: =I8*J8 -> 3686520 | L8: 0.055 | M8: =K8*(1-L8) -> 3483761.4 | N8: 0.673 | O8: =M8*N8 -> 2344571.4 | P8: =M8-O8 -> 1139190 | Q8: Pagado | R8: =TEXT(A8,"YYYY-MM") -> 2025-01
A9: 45662 | B9: FAC008 | C9: C027 | D9: Hipermercado El Cacique | E9: P032 | F9: Chocolate en Polvo para Bebida Bolsa 400g | G9: Marca propia | H9: Supermercado | I9: 347 | J9: 4450 | K9: =I9*J9 -> 1544150 | L9: 0.07 | M9: =K9*(1-L9) -> 1436059.5 | N9: 0.746 | O9: =M9*N9 -> 1071300.4 | P9: =M9-O9 -> 364759.11 | Q9: Pagado | R9: =TEXT(A9,"YYYY-MM") -> 2025-01
A10: 45664 | B10: FAC009 | C10: C020 | D10: Hipermercado El Rey | E10: P013 | F10: Atún en Lata Lata 170g | G10: Alimentos | H10: Supermercado | I10: 159 | J10: 9950 | K10: =I10*J10 -> 1582050 | L10: 0 | M10: =K10*(1-L10) -> 1582050 | N10: 0.748 | O10: =M10*N10 -> 1183373.4 | P10: =M10-O10 -> 398676.6 | Q10: Pagado | R10: =TEXT(A10,"YYYY-MM") -> 2025-01
A11: 45664 | B11: FAC010 | C11: C039 | D11: Colegio El Bosque | E11: P012 | F11: Salchicha Tipo Viena Paquete 500g | G11: Alimentos | H11: Institucional | I11: 764 | J11: 6740 | K11: =I11*J11 -> 5149360 | L11: 0.144 | M11: =K11*(1-L11) -> 4407852.2 | N11: 0.703 | O11: =M11*N11 -> 3098720.1 | P11: =M11-O11 -> 1309132.1 | Q11: Pagado | R11: =TEXT(A11,"YYYY-MM") -> 2025-01
A12: 45666 | B12: FAC011 | C12: Supuestos: % Incremento 2025 e % Cartera Vencida son valores de entrada (fuente: simulación para demo/analítica, no datos reales de Andina Foods S.A.S.). Cartera Vencida (COP) = Ventas 2024 × % Cartera Vencida. Ingresos 2025 (COP) = Ventas 2024 × (1 + % Incremento 2025). | E12: P010 | F12: Café Instantáneo Frasco 170g | G12: Bebidas | H12: Tienda tradicional | I12: 170 | J12: 3600 | K12: =I12*J12 -> 612000 | L12: 0 | M12: =K12*(1-L12) -> 612000 | N12: 0.641 | O12: =M12*N12 -> 392292 | P12: =M12-O12 -> 219708 | Q12: Pagado | R12: =TEXT(A12,"YYYY-MM") -> 2025-01
A13: 45666 | B13: FAC012 | C13: C097 | D13: Autoservicio Don Pedro | E13: P007 | F13: Chocolate de Mesa Barra 500g | G13: Alimentos | H13: Tienda tradicional | I13: 428 | J13: 2400 | K13: =I13*J13 -> 1027200 | L13: 0.073 | M13: =K13*(1-L13) -> 952214.4 | N13: 0.716 | O13: =M13*N13 -> 681785.51 | P13: =M13-O13 -> 270428.89 | Q13: Pendiente | R13: =TEXT(A13,"YYYY-MM") -> 2025-01
A14: 45668 | B14: FAC013 | C14: C043 | D14: Autoservicios Central | E14: P014 | F14: Galletas de Chocolate Paquete 200g | G14: Alimentos | H14: Supermercado | I14: 663 | J14: 11620 | K14: =I14*J14 -> 7704060 | L14: 0.102 | M14: =K14*(1-L14) -> 6918245.9 | N14: 0.659 | O14: =M14*N14 -> 4559124 | P14: =M14-O14 -> 2359121.8 | Q14: Pagado | R14: =TEXT(A14,"YYYY-MM") -> 2025-01
A15: 45668 | B15: FAC014 | C15: C122 | D15: Panadería San Fernando | E15: P082 | F15: Café Instantáneo Frasco 170g (76) | G15: Bebidas | H15: Institucional | I15: 622 | J15: 8000 | K15: =I15*J15 -> 4976000 | L15: 0.119 | M15: =K15*(1-L15) -> 4383856 | N15: 0.713 | O15: =M15*N15 -> 3125689.3 | P15: =M15-O15 -> 1258166.7 | Q15: Pagado | R15: =TEXT(A15,"YYYY-MM") -> 2025-01
A16: 45669 | B16: FAC015 | C16: C006 | D16: Tienda La Esquina | E16: P102 | F16: Café Instantáneo Frasco 170g (77) | G16: Bebidas | H16: Tienda tradicional | I16: 747 | J16: 2860 | K16: =I16*J16 -> 2136420 | L16: 0.121 | M16: =K16*(1-L16) -> 1877913.2 | N16: 0.705 | O16: =M16*N16 -> 1323928.8 | P16: =M16-O16 -> 553984.39 | Q16: Pagado | R16: =TEXT(A16,"YYYY-MM") -> 2025-01
A17: 45669 | B17: FAC016 | C17: C138 | D17: Autoservicios La 15 | E17: P039 | F17: Gaseosa Sabor Cola 1.5L | G17: Bebidas | H17: Supermercado | I17: 395 | J17: 7530 | K17: =I17*J17 -> 2974350 | L17: 0.095 | M17: =K17*(1-L17) -> 2691786.8 | N17: 0.723 | O17: =M17*N17 -> 1946161.8 | P17: =M17-O17 -> 745624.93 | Q17: Pagado | R17: =TEXT(A17,"YYYY-MM") -> 2025-01
A18: 45671 | B18: FAC017 | C18: C008 | D18: Autoservicios El Cacique | E18: P042 | F18: Té Frío de Limón 1.5L | G18: Bebidas | H18: Supermercado | I18: 579 | J18: 1770 | K18: =I18*J18 -> 1024830 | L18: 0.06 | M18: =K18*(1-L18) -> 963340.2 | N18: 0.62 | O18: =M18*N18 -> 597270.92 | P18: =M18-O18 -> 366069.28 | Q18: Pagado | R18: =TEXT(A18,"YYYY-MM") -> 2025-01
A19: 45672 | B19: FAC018 | C19: C116 | D19: Supermercado La Canasta | E19: P115 | F19: Café Instantáneo Frasco 170g (81) | G19: Bebidas | H19: Supermercado | I19: 200 | J19: 3270 | K19: =I19*J19 -> 654000 | L19: 0 | M19: =K19*(1-L19) -> 654000 | N19: 0.667 | O19: =M19*N19 -> 436218 | P19: =M19-O19 -> 217782 | Q19: Pagado | R19: =TEXT(A19,"YYYY-MM") -> 2025-01
A20: 45674 | B20: FAC019 | C20: C005 | D20: Hipermercado La Bonanza | E20: P023 | F20: Agua Sin Gas 1L | G20: Bebidas | H20: Supermercado | I20: 165 | J20: 3450 | K20: =I20*J20 -> 569250 | L20: 0 | M20: =K20*(1-L20) -> 569250 | N20: 0.636 | O20: =M20*N20 -> 362043 | P20: =M20-O20 -> 207207 | Q20: Pagado | R20: =TEXT(A20,"YYYY-MM") -> 2025-01
A21: 45675 | B21: FAC020 | C21: C015 | D21: Hipermercado La Canasta | E21: P115 | F21: Café Instantáneo Frasco 170g (81) | G21: Bebidas | H21: Supermercado | I21: 561 | J21: 3270 | K21: =I21*J21 -> 1834470 | L21: 0.04 | M21: =K21*(1-L21) -> 1761091.2 | N21: 0.685 | O21: =M21*N21 -> 1206347.5 | P21: =M21-O21 -> 554743.73 | Q21: Pagado | R21: =TEXT(A21,"YYYY-MM") -> 2025-01
A22: 45675 | B22: FAC021 | C22: C044 | D22: Clínica El Marqués | E22: P110 | F22: Atún en Lata Lata 170g (99) | G22: Alimentos | H22: Institucional | I22: 489 | J22: 14670 | K22: =I22*J22 -> 7173630 | L22: 0.078 | M22: =K22*(1-L22) -> 6614086.9 | N22: 0.698 | O22: =M22*N22 -> 4616632.6 | P22: =M22-O22 -> 1997454.2 | Q22: Pagado | R22: =TEXT(A22,"YYYY-MM") -> 2025-01
A23: 45678 | B23: FAC022 | C23: C138 | D23: Autoservicios La 15 | E23: P112 | F23: Agua Saborizada Limón 500ml (18) | G23: Marca propia | H23: Supermercado | I23: 329 | J23: 8910 | K23: =I23*J23 -> 2931390 | L23: 0.073 | M23: =K23*(1-L23) -> 2717398.5 | N23: 0.683 | O23: =M23*N23 -> 1855983.2 | P23: =M23-O23 -> 861415.33 | Q23: Pagado | R23: =TEXT(A23,"YYYY-MM") -> 2025-01
A24: 45678 | B24: FAC023 | C24: C147 | D24: Minimercado La Bendición | E24: P111 | F24: Agua Saborizada Limón 500ml (39) | G24: Bebidas | H24: Tienda tradicional | I24: 179 | J24: 6960 | K24: =I24*J24 -> 1245840 | L24: 0.006 | M24: =K24*(1-L24) -> 1238365 | N24: 0.622 | O24: =M24*N24 -> 770263.01 | P24: =M24-O24 -> 468101.95 | Q24: Pagado | R24: =TEXT(A24,"YYYY-MM") -> 2025-01
... A256: 45871 | B256: FAC255 | C256: C144 | D256: Hipermercado Central | E256: P070 | F256: Bebida Energizante 250ml (20) | G256: Bebidas | H256: Supermercado | I256: 562 | J256: 3410 | K256: =I256*J256 -> 1916420 | L256: 0.043 | M256: =K256*(1-L256) -> 1834013.9 | N256: 0.74 | O256: =M256*N256 -> 1357170.3 | P256: =M256-O256 -> 476843.62 | Q256: Pagado | R256: =TEXT(A256,"YYYY-MM") -> 2025-08
A257: 45871 | B257: FAC256 | C257: Supuestos: % Incremento 2025 e % Cartera Vencida son valores de entrada (fuente: simulación para demo/analítica, no datos reales de Andina Foods S.A.S.). Cartera Vencida (COP) = Ventas 2024 × % Cartera Vencida. Ingresos 2025 (COP) = Ventas 2024 × (1 + % Incremento 2025). | E257: P062 | F257: Agua Saborizada Limón 500ml (83) | G257: Bebidas | H257: Tienda tradicional | I257: 241 | J257: 1700 | K257: =I257*J257 -> 409700 | L257: 0 | M257: =K257*(1-L257) -> 409700 | N257: 0.61 | O257: =M257*N257 -> 249917 | P257: =M257-O257 -> 159783 | Q257: Pendiente | R257: =TEXT(A257,"YYYY-MM") -> 2025-08
A258: 45873 | B258: FAC257 | C258: C059 | D258: Supermercado El Rey | E258: P095 | F258: Refresco de Manzana 1.5L (36) | G258: Marca propia | H258: Supermercado | I258: 139 | J258: 6000 | K258: =I258*J258 -> 834000 | L258: 0 | M258: =K258*(1-L258) -> 834000 | N258: 0.677 | O258: =M258*N258 -> 564618 | P258: =M258-O258 -> 269382 | Q258: Pagado | R258: =TEXT(A258,"YYYY-MM") -> 2025-08
A259: 45873 | B259: FAC258 | C259: C038 | D259: Supermercado El Cacique | E259: P074 | F259: Galletas de Chocolate Paquete 200g (74) | G259: Alimentos | H259: Supermercado | I259: 765 | J259: 4370 | K259: =I259*J259 -> 3343050 | L259: 0.115 | M259: =K259*(1-L259) -> 2958599.2 | N259: 0.721 | O259: =M259*N259 -> 2133150.1 | P259: =M259-O259 -> 825449.19 | Q259: Pagado | R259: =TEXT(A259,"YYYY-MM") -> 2025-08
A260: 45874 | B260: FAC259 | C260: C148 | D260: Hipermercado Mercar | E260: P008 | F260: Snack de Papa Bolsa 150g | G260: Marca propia | H260: Supermercado | I260: 165 | J260: 18190 | K260: =I260*J260 -> 3001350 | L260: 0 | M260: =K260*(1-L260) -> 3001350 | N260: 0.695 | O260: =M260*N260 -> 2085938.2 | P260: =M260-O260 -> 915411.75 | Q260: Vencido | R260: =TEXT(A260,"YYYY-MM") -> 2025-08
A261: 45875 | B261: FAC260 | C261: C094 | D261: Hipermercado La Canasta | E261: P115 | F261: Café Instantáneo Frasco 170g (81) | G261: Bebidas | H261: Supermercado | I261: 822 | J261: 3270 | K261: =I261*J261 -> 2687940 | L261: 0.136 | M261: =K261*(1-L261) -> 2322380.2 | N261: 0.676 | O261: =M261*N261 -> 1569929 | P261: =M261-O261 -> 752451.17 | Q261: Pagado | R261: =TEXT(A261,"YYYY-MM") -> 2025-08
A262: 45875 | B262: FAC261 | C262: C074 | D262: Hipermercado La 15 | E262: P097 | F262: Enjuague Bucal Botella 500ml (41) | G262: Cuidado Personal | H262: Supermercado | I262: 195 | J262: 9310 | K262: =I262*J262 -> 1815450 | L262: 0 | M262: =K262*(1-L262) -> 1815450 | N262: 0.608 | O262: =M262*N262 -> 1103793.6 | P262: =M262-O262 -> 711656.4 | Q262: Pagado | R262: =TEXT(A262,"YYYY-MM") -> 2025-08
A263: 45877 | B263: FAC262 | C263: C014 | D263: Autoservicio El Faro | E263: P003 | F263: Yogurt Bebible Fresa 200ml | G263: Bebidas | H263: Tienda tradicional | I263: 523 | J263: 9460 | K263: =I263*J263 -> 4947580 | L263: 0.077 | M263: =K263*(1-L263) -> 4566616.3 | N263: 0.745 | O263: =M263*N263 -> 3402129.2 | P263: =M263-O263 -> 1164487.2 | Q263: Pendiente | R263: =TEXT(A263,"YYYY-MM") -> 2025-08
A264: 45878 | B264: FAC263 | C264: C020 | D264: Hipermercado El Rey | E264: P037 | F264: Jugo de Naranja Natural 200ml | G264: Marca propia | H264: Supermercado | I264: 21 | J264: 7430 | K264: =I264*J264 -> 156030 | L264: 0 | M264: =K264*(1-L264) -> 156030 | N264: 0.75 | O264: =M264*N264 -> 117022.5 | P264: =M264-O264 -> 39007.5 | Q264: Pagado | R264: =TEXT(A264,"YYYY-MM") -> 2025-08
A265: 45878 | B265: FAC264 | C265: C083 | D265: Deposito San Roque | E265: P061 | F265: Yogurt Bebible Fresa 200ml (15) | G265: Bebidas | H265: Tienda tradicional | I265: 238 | J265: 5040 | K265: =I265*J265 -> 1199520 | L265: 0 | M265: =K265*(1-L265) -> 1199520 | N265: 0.659 | O265: =M265*N265 -> 790483.68 | P265: =M265-O265 -> 409036.32 | Q265: Pendiente | R265: =TEXT(A265,"YYYY-MM") -> 2025-08
A266: 45879 | B266: FAC265 | C266: C135 | D266: Minimercado Don Pedro | E266: P017 | F266: Bebida Energizante 250ml | G266: Marca propia | H266: Tienda tradicional | I266: 93 | J266: 9680 | K266: =I266*J266 -> 900240 | L266: 0.019 | M266: =K266*(1-L266) -> 883135.44 | N266: 0.661 | O266: =M266*N266 -> 583752.53 | P266: =M266-O266 -> 299382.91 | Q266: Pagado | R266: =TEXT(A266,"YYYY-MM") -> 2025-08
A267: 45881 | B267: FAC266 | C267: C052 | D267: Minimercado La 84 | E267: P027 | F267: Galletas Saladas Paquete 300g | G267: Alimentos | H267: Tienda tradicional | I267: 377 | J267: 8920 | K267: =I267*J267 -> 3362840 | L267: 0.053 | M267: =K267*(1-L267) -> 3184609.5 | N267: 0.676 | O267: =M267*N267 -> 2152796 | P267: =M267-O267 -> 1031813.5 | Q267: Pendiente | R267: =TEXT(A267,"YYYY-MM") -> 2025-08
A268: 45881 | B268: FAC267 | C268: C033 | D268: Super Mercar | E268: P004 | F268: Arroz Blanco Bolsa 1kg | G268: Alimentos | H268: Supermercado | I268: 438 | J268: 4850 | K268: =I268*J268 -> 2124300 | L268: 0.079 | M268: =K268*(1-L268) -> 1956480.3 | N268: 0.619 | O268: =M268*N268 -> 1211061.3 | P268: =M268-O268 -> 745418.99 | Q268: Pagado | R268: =TEXT(A268,"YYYY-MM") -> 2025-08
A269: 45882 | B269: FAC268 | C269: C054 | D269: Hipermercado La Bonanza | E269: P106 | F269: Bebida Energizante 250ml (76) | G269: Bebidas | H269: Supermercado | I269: 950 | J269: 4280 | K269: =I269*J269 -> 4066000 | L269: 0.118 | M269: =K269*(1-L269) -> 3586212 | N269: 0.641 | O269: =M269*N269 -> 2298761.9 | P269: =M269-O269 -> 1287450.1 | Q269: Pagado | R269: =TEXT(A269,"YYYY-MM") -> 2025-08
... A301: 45900 | B301: FAC300 | C301: C036 | D301: Autoservicio El Trebol | E301: P113 | F301: Arroz Blanco Bolsa 1kg (11) | G301: Alimentos | H301: Tienda tradicional | I301: 147 | J301: 3490 | K301: =I301*J301 -> 513030 | L301: 0 | M301: =K301*(1-L301) -> 513030 | N301: 0.639 | O301: =M301*N301 -> 327826.17 | P301: =M301-O301 -> 185203.83 | Q301: Pagado | R301: =TEXT(A301,"YYYY-MM") -> 2025-08
A303: Supuestos: Cantidad, Descuento % y % Costo COGS son valores de entrada (fuente: simulación para demo/analítica, no transacciones reales de Andina Foods S.A.S.). Valor Total = Cantidad × Valor Unitario. Valor Neto = Valor Total × (1 - Descuento %). Costo COGS = Valor Neto × % Costo COGS (rango 60%-75%). Utilidad Bruta = Valor Neto - Costo COGS. Cliente y Producto son consistentes con los archivos Clientes_Andina_Foods.xlsx y Productos_Andina_Foods.xlsx generados previamente.

Sheet Resumen Mensual
A1: Resumen Mensual — Andina Foods S.A.S. (Enero-Agosto 2025)
A3: Mes | B3: N° Facturas | C3: Ingresos (Valor Neto) | D3: Costos (COGS) | E3: Utilidad Bruta | F3: Margen Bruto %
A4: Enero | B4: =COUNTIF(Transacciones!R2:R301,"2025-01") -> 32 | C4: =SUMIFS(Transacciones!M2:M301,Transacciones!R2:R301,"2025-01") -> 88883007 | D4: =SUMIFS(Transacciones!O2:O301,Transacciones!R2:R301,"2025-01") -> 61125877 | E4: =C4-D4 -> 27757130 | F4: =E4/C4 -> 0.31228837
A5: Febrero | B5: =COUNTIF(Transacciones!R2:R301,"2025-02") -> 33 | C5: =SUMIFS(Transacciones!M2:M301,Transacciones!R2:R301,"2025-02") -> 1.027066e+08 | D5: =SUMIFS(Transacciones!O2:O301,Transacciones!R2:R301,"2025-02") -> 67934290 | E5: =C5-D5 -> 34772306 | F5: =E5/C5 -> 0.33855962
A6: Marzo | B6: =COUNTIF(Transacciones!R2:R301,"2025-03") -> 35 | C6: =SUMIFS(Transacciones!M2:M301,Transacciones!R2:R301,"2025-03") -> 1.0180983e+08 | D6: =SUMIFS(Transacciones!O2:O301,Transacciones!R2:R301,"2025-03") -> 67727441 | E6: =C6-D6 -> 34082392 | F6: =E6/C6 -> 0.33476523
A7: Abril | B7: =COUNTIF(Transacciones!R2:R301,"2025-04") -> 36 | C7: =SUMIFS(Transacciones!M2:M301,Transacciones!R2:R301,"2025-04") -> 1.0171302e+08 | D7: =SUMIFS(Transacciones!O2:O301,Transacciones!R2:R301,"2025-04") -> 67361311 | E7: =C7-D7 -> 34351704 | F7: =E7/C7 -> 0.33773164
A8: Mayo | B8: =COUNTIF(Transacciones!R2:R301,"2025-05") -> 37 | C8: =SUMIFS(Transacciones!M2:M301,Transacciones!R2:R301,"2025-05") -> 98179444 | D8: =SUMIFS(Transacciones!O2:O301,Transacciones!R2:R301,"2025-05") -> 66555643 | E8: =C8-D8 -> 31623801 | F8: =E8/C8 -> 0.32210206
A9: Junio | B9: =COUNTIF(Transacciones!R2:R301,"2025-06") -> 39 | C9: =SUMIFS(Transacciones!M2:M301,Transacciones!R2:R301,"2025-06") -> 97488833 | D9: =SUMIFS(Transacciones!O2:O301,Transacciones!R2:R301,"2025-06") -> 64578562 | E9: =C9-D9 -> 32910271 | F9: =E9/C9 -> 0.33757991
A10: Julio | B10: =COUNTIF(Transacciones!R2:R301,"2025-07") -> 40 | C10: =SUMIFS(Transacciones!M2:M301,Transacciones!R2:R301,"2025-07") -> 1.2533198e+08 | D10: =SUMIFS(Transacciones!O2:O301,Transacciones!R2:R301,"2025-07") -> 83480765 | E10: =C10-D10 -> 41851214 | F10: =E10/C10 -> 0.33392287
A11: Agosto | B11: =COUNTIF(Transacciones!R2:R301,"2025-08") -> 48 | C11: =SUMIFS(Transacciones!M2:M301,Transacciones!R2:R301,"2025-08") -> 1.1237446e+08 | D11: =SUMIFS(Transacciones!O2:O301,Transacciones!R2:R301,"2025-08") -> 75769225 | E11: =C11-D11 -> 36605233 | F11: =E11/C11 -> 0.32574336
A12: TOTAL / PROMEDIO | B12: =SUM(B4:B11) -> 300 | C12: =SUM(C4:C11) -> 8.2848717e+08 | D12: =SUM(D4:D11) -> 5.5453311e+08 | E12: =C12-D12 -> 2.7395405e+08 | F12: =E12/C12 -> 0.33066783
A15: Ingresos (Valor Neto) por Canal y Mes
A16: Mes | B16: Tienda tradicional | C16: Supermercado | D16: Institucional | E16: Total
A17: Enero | B17: =SUMIFS(Transacciones!M2:M301,Transacciones!R2:R301,"2025-01",Transacciones!H2:H301,"Tienda tradicional") -> 20565669 | C17: =SUMIFS(Transacciones!M2:M301,Transacciones!R2:R301,"2025-01",Transacciones!H2:H301,"Supermercado") -> 42022638 | D17: =SUMIFS(Transacciones!M2:M301,Transacciones!R2:R301,"2025-01",Transacciones!H2:H301,"Institucional") -> 26294700 | E17: =SUM(B17:D17) -> 88883007
A18: Febrero | B18: =SUMIFS(Transacciones!M2:M301,Transacciones!R2:R301,"2025-02",Transacciones!H2:H301,"Tienda tradicional") -> 20531243 | C18: =SUMIFS(Transacciones!M2:M301,Transacciones!R2:R301,"2025-02",Transacciones!H2:H301,"Supermercado") -> 40524923 | D18: =SUMIFS(Transacciones!M2:M301,Transacciones!R2:R301,"2025-02",Transacciones!H2:H301,"Institucional") -> 41650430 | E18: =SUM(B18:D18) -> 1.027066e+08
A19: Marzo | B19: =SUMIFS(Transacciones!M2:M301,Transacciones!R2:R301,"2025-03",Transacciones!H2:H301,"Tienda tradicional") -> 18355207 | C19: =SUMIFS(Transacciones!M2:M301,Transacciones!R2:R301,"2025-03",Transacciones!H2:H301,"Supermercado") -> 75439383 | D19: =SUMIFS(Transacciones!M2:M301,Transacciones!R2:R301,"2025-03",Transacciones!H2:H301,"Institucional") -> 8015243.3 | E19: =SUM(B19:D19) -> 1.0180983e+08
A20: Abril | B20: =SUMIFS(Transacciones!M2:M301,Transacciones!R2:R301,"2025-04",Transacciones!H2:H301,"Tienda tradicional") -> 22629427 | C20: =SUMIFS(Transacciones!M2:M301,Transacciones!R2:R301,"2025-04",Transacciones!H2:H301,"Supermercado") -> 50006705 | D20: =SUMIFS(Transacciones!M2:M301,Transacciones!R2:R301,"2025-04",Transacciones!H2:H301,"Institucional") -> 29076883 | E20: =SUM(B20:D20) -> 1.0171302e+08
A21: Mayo | B21: =SUMIFS(Transacciones!M2:M301,Transacciones!R2:R301,"2025-05",Transacciones!H2:H301,"Tienda tradicional") -> 32404384 | C21: =SUMIFS(Transacciones!M2:M301,Transacciones!R2:R301,"2025-05",Transacciones!H2:H301,"Supermercado") -> 46056423 | D21: =SUMIFS(Transacciones!M2:M301,Transacciones!R2:R301,"2025-05",Transacciones!H2:H301,"Institucional") -> 19718638 | E21: =SUM(B21:D21) -> 98179444
A22: Junio | B22: =SUMIFS(Transacciones!M2:M301,Transacciones!R2:R301,"2025-06",Transacciones!H2:H301,"Tienda tradicional") -> 33184047 | C22: =SUMIFS(Transacciones!M2:M301,Transacciones!R2:R301,"2025-06",Transacciones!H2:H301,"Supermercado") -> 38013549 | D22: =SUMIFS(Transacciones!M2:M301,Transacciones!R2:R301,"2025-06",Transacciones!H2:H301,"Institucional") -> 26291238 | E22: =SUM(B22:D22) -> 97488833
A23: Julio | B23: =SUMIFS(Transacciones!M2:M301,Transacciones!R2:R301,"2025-07",Transacciones!H2:H301,"Tienda tradicional") -> 37692072 | C23: =SUMIFS(Transacciones!M2:M301,Transacciones!R2:R301,"2025-07",Transacciones!H2:H301,"Supermercado") -> 73437850 | D23: =SUMIFS(Transacciones!M2:M301,Transacciones!R2:R301,"2025-07",Transacciones!H2:H301,"Institucional") -> 14202057 | E23: =SUM(B23:D23) -> 1.2533198e+08
A24: Agosto | B24: =SUMIFS(Transacciones!M2:M301,Transacciones!R2:R301,"2025-08",Transacciones!H2:H301,"Tienda tradicional") -> 28000175 | C24: =SUMIFS(Transacciones!M2:M301,Transacciones!R2:R301,"2025-08",Transacciones!H2:H301,"Supermercado") -> 77203556 | D24: =SUMIFS(Transacciones!M2:M301,Transacciones!R2:R301,"2025-08",Transacciones!H2:H301,"Institucional") -> 7170727.3 | E24: =SUM(B24:D24) -> 1.1237446e+08
A25: TOTAL | B25: =SUM(B17:B24) -> 2.1336222e+08 | C25: =SUM(C17:C24) -> 4.4270503e+08 | D25: =SUM(D17:D24) -> 1.7241992e+08 | E25: =SUM(E17:E24) -> 8.2848717e+08
A28: Ingresos (Valor Neto) por Categoría de Producto y Mes
A29: Mes | B29: Bebidas | C29: Alimentos | D29: Aseo | E29: Cuidado Personal | F29: Marca propia | G29: Total
A30: Enero | B30: =SUMIFS(Transacciones!M2:M301,Transacciones!R2:R301,"2025-01",Transacciones!G2:G301,"Bebidas") -> 32758893 | C30: =SUMIFS(Transacciones!M2:M301,Transacciones!R2:R301,"2025-01",Transacciones!G2:G301,"Alimentos") -> 49651646 | D30: =SUMIFS(Transacciones!M2:M301,Transacciones!R2:R301,"2025-01",Transacciones!G2:G301,"Aseo") -> 0 | E30: =SUMIFS(Transacciones!M2:M301,Transacciones!R2:R301,"2025-01",Transacciones!G2:G301,"Cuidado Personal") -> 456190 | F30: =SUMIFS(Transacciones!M2:M301,Transacciones!R2:R301,"2025-01",Transacciones!G2:G301,"Marca propia") -> 6016278 | G30: =SUM(B30:F30) -> 88883007
A31: Febrero | B31: =SUMIFS(Transacciones!M2:M301,Transacciones!R2:R301,"2025-02",Transacciones!G2:G301,"Bebidas") -> 26230752 | C31: =SUMIFS(Transacciones!M2:M301,Transacciones!R2:R301,"2025-02",Transacciones!G2:G301,"Alimentos") -> 57995550 | D31: =SUMIFS(Transacciones!M2:M301,Transacciones!R2:R301,"2025-02",Transacciones!G2:G301,"Aseo") -> 8847546.2 | E31: =SUMIFS(Transacciones!M2:M301,Transacciones!R2:R301,"2025-02",Transacciones!G2:G301,"Cuidado Personal") -> 6777362.5 | F31: =SUMIFS(Transacciones!M2:M301,Transacciones!R2:R301,"2025-02",Transacciones!G2:G301,"Marca propia") -> 2855385.6 | G31: =SUM(B31:F31) -> 1.027066e+08
A32: Marzo | B32: =SUMIFS(Transacciones!M2:M301,Transacciones!R2:R301,"2025-03",Transacciones!G2:G301,"Bebidas") -> 30269116 | C32: =SUMIFS(Transacciones!M2:M301,Transacciones!R2:R301,"2025-03",Transacciones!G2:G301,"Alimentos") -> 63766984 | D32: =SUMIFS(Transacciones!M2:M301,Transacciones!R2:R301,"2025-03",Transacciones!G2:G301,"Aseo") -> 5436225 | E32: =SUMIFS(Transacciones!M2:M301,Transacciones!R2:R301,"2025-03",Transacciones!G2:G301,"Cuidado Personal") -> 0 | F32: =SUMIFS(Transacciones!M2:M301,Transacciones!R2:R301,"2025-03",Transacciones!G2:G301,"Marca propia") -> 2337507.9 | G32: =SUM(B32:F32) -> 1.0180983e+08
A33: Abril | B33: =SUMIFS(Transacciones!M2:M301,Transacciones!R2:R301,"2025-04",Transacciones!G2:G301,"Bebidas") -> 45660574 | C33: =SUMIFS(Transacciones!M2:M301,Transacciones!R2:R301,"2025-04",Transacciones!G2:G301,"Alimentos") -> 47307859 | D33: =SUMIFS(Transacciones!M2:M301,Transacciones!R2:R301,"2025-04",Transacciones!G2:G301,"Aseo") -> 0 | E33: =SUMIFS(Transacciones!M2:M301,Transacciones!R2:R301,"2025-04",Transacciones!G2:G301,"Cuidado Personal") -> 6811439.2 | F33: =SUMIFS(Transacciones!M2:M301,Transacciones!R2:R301,"2025-04",Transacciones!G2:G301,"Marca propia") -> 1933142.2 | G33: =SUM(B33:F33) -> 1.0171302e+08
A34: Mayo | B34: =SUMIFS(Transacciones!M2:M301,Transacciones!R2:R301,"2025-05",Transacciones!G2:G301,"Bebidas") -> 58182973 | C34: =SUMIFS(Transacciones!M2:M301,Transacciones!R2:R301,"2025-05",Transacciones!G2:G301,"Alimentos") -> 31851426 | D34: =SUMIFS(Transacciones!M2:M301,Transacciones!R2:R301,"2025-05",Transacciones!G2:G301,"Aseo") -> 1588060 | E34: =SUMIFS(Transacciones!M2:M301,Transacciones!R2:R301,"2025-05",Transacciones!G2:G301,"Cuidado Personal") -> 1417672.2 | F34: =SUMIFS(Transacciones!M2:M301,Transacciones!R2:R301,"2025-05",Transacciones!G2:G301,"Marca propia") -> 5139313.1 | G34: =SUM(B34:F34) -> 98179444
A35: Junio | B35: =SUMIFS(Transacciones!M2:M301,Transacciones!R2:R301,"2025-06",Transacciones!G2:G301,"Bebidas") -> 16954621 | C35: =SUMIFS(Transacciones!M2:M301,Transacciones!R2:R301,"2025-06",Transacciones!G2:G301,"Alimentos") -> 38448662 | D35: =SUMIFS(Transacciones!M2:M301,Transacciones!R2:R301,"2025-06",Transacciones!G2:G301,"Aseo") -> 19098754 | E35: =SUMIFS(Transacciones!M2:M301,Transacciones!R2:R301,"2025-06",Transacciones!G2:G301,"Cuidado Personal") -> 1845180 | F35: =SUMIFS(Transacciones!M2:M301,Transacciones!R2:R301,"2025-06",Transacciones!G2:G301,"Marca propia") -> 21141616 | G35: =SUM(B35:F35) -> 97488833
A36: Julio | B36: =SUMIFS(Transacciones!M2:M301,Transacciones!R2:R301,"2025-07",Transacciones!G2:G301,"Bebidas") -> 35140286 | C36: =SUMIFS(Transacciones!M2:M301,Transacciones!R2:R301,"2025-07",Transacciones!G2:G301,"Alimentos") -> 74171556 | D36: =SUMIFS(Transacciones!M2:M301,Transacciones!R2:R301,"2025-07",Transacciones!G2:G301,"Aseo") -> 4609090 | E36: =SUMIFS(Transacciones!M2:M301,Transacciones!R2:R301,"2025-07",Transacciones!G2:G301,"Cuidado Personal") -> 4731228.1 | F36: =SUMIFS(Transacciones!M2:M301,Transacciones!R2:R301,"2025-07",Transacciones!G2:G301,"Marca propia") -> 6679819.3 | G36: =SUM(B36:F36) -> 1.2533198e+08
A37: Agosto | B37: =SUMIFS(Transacciones!M2:M301,Transacciones!R2:R301,"2025-08",Transacciones!G2:G301,"Bebidas") -> 42262785 | C37: =SUMIFS(Transacciones!M2:M301,Transacciones!R2:R301,"2025-08",Transacciones!G2:G301,"Alimentos") -> 44938617 | D37: =SUMIFS(Transacciones!M2:M301,Transacciones!R2:R301,"2025-08",Transacciones!G2:G301,"Aseo") -> 1623440 | E37: =SUMIFS(Transacciones!M2:M301,Transacciones!R2:R301,"2025-08",Transacciones!G2:G301,"Cuidado Personal") -> 4807102.5 | F37: =SUMIFS(Transacciones!M2:M301,Transacciones!R2:R301,"2025-08",Transacciones!G2:G301,"Marca propia") -> 18742514 | G37: =SUM(B37:F37) -> 1.1237446e+08
A38: TOTAL | B38: =SUM(B30:B37) -> 2.8746e+08 | C38: =SUM(C30:C37) -> 4.081323e+08 | D38: =SUM(D30:D37) -> 41203116 | E38: =SUM(E30:E37) -> 26846175 | F38: =SUM(F30:F37) -> 64845576 | G38: =SUM(G30:G37) -> 8.2848717e+08
A41: Estado de Facturación (Enero-Agosto 2025)
A42: Total Pagado (COP) | B42: =SUMIF(Transacciones!Q2:Q301,"Pagado",Transacciones!M2:M301) -> 7.3323507e+08
A43: Total Pendiente (COP) | B43: =SUMIF(Transacciones!Q2:Q301,"Pendiente",Transacciones!M2:M301) -> 59794444
A44: Total Vencido (COP) | B44: =SUMIF(Transacciones!Q2:Q301,"Vencido",Transacciones!M2:M301) -> 35457654
A46: Nota: datos simulados con fines de demostración / analítica del programa Master IA Local. No corresponden a transacciones reales de Andina Foods S.A.S.
